{"apetown": [{"id": 1004862, "mc": 1500, "oc": 158}], "apexpredatorgaming": [{"id": 1012825, "mc": 1776, "oc": 382}], "apexlegendsgermany": [{"id": 1021139, "mc": 25020, "oc": 3164}], "apk": [{"id": 1049444, "mc": 857, "oc": 124}], "apple": [{"id": 1052921, "mc": 90930, "oc": 9650}], "aphelionmc-921578028226715658": [{"id": 1062564, "mc": 1860, "oc": 111}], "appeals": [{"id": 1066028, "mc": 600, "oc": 69}], "apexhk": [{"id": 1078729, "mc": 4244, "oc": 1058}], "apostles": [{"id": 1086497, "mc": 1901, "oc": 560}], "apxx": [{"id": 1090954, "mc": 2286, "oc": 649}], "applecheats": [{"id": 1102155, "mc": 3462, "oc": 119}], "apg": [{"id": 1112876, "mc": 20251, "oc": 1122}], "apefederation": [{"id": 1115032, "mc": 283, "oc": 51}], "apmk": [{"id": 1138784, "mc": 139, "oc": 46}], "apateu": [{"id": 1139725, "mc": 841, "oc": 95}], "aponism": [{"id": 1162754, "mc": 217, "oc": 26}], "aphroditeservices": [{"id": 1168796, "mc": 18610, "oc": 1691}], "apollo-hq-923425920096800788": [{"id": 1191168, "mc": 25745, "oc": 992}], "apocalypse-746775712018727062": [{"id": 1193749, "mc": 2961, "oc": 539}], "apacproleague": [{"id": 1202025, "mc": 487, "oc": 274}], "apenasumreact": [{"id": 1202046, "mc": 5029, "oc": 168}], "apt214": [{"id": 1202070, "mc": 228, "oc": 94}], "appleonfire": [{"id": 1202141, "mc": 93, "oc": 24}], "apsara": [{"id": 1202203, "mc": 425, "oc": 44}], "apexcry": [{"id": 1202576, "mc": 42, "oc": 2}], "apkmethod": [{"id": 1202615, "mc": 2727, "oc": 535}], "apexracing": [{"id": 1202678, "mc": 268, "oc": 30}], "apexop": [{"id": 1202952, "mc": 2104, "oc": 266}], "apricus": [{"id": 1226214, "mc": 81, "oc": 17}]}