{"mrntv": [{"id": 1000083, "mc": 456, "oc": 22}], "mr": [{"id": 1000148, "mc": 181, "oc": 11}, {"id": 1001190, "mc": 21, "oc": 4}, {"id": 1001827, "mc": 14, "oc": 6}, {"id": 1002503, "mc": 197, "oc": 16}, {"id": 1002778, "mc": 395, "oc": 60}, {"id": 1003421, "mc": 1580, "oc": 118}, {"id": 1003840, "mc": 25, "oc": 10}, {"id": 1003986, "mc": 37, "oc": 7}, {"id": 1006016, "mc": 42, "oc": 3}, {"id": 1008435, "mc": 25, "oc": 1}, {"id": 1009509, "mc": 497, "oc": 120}, {"id": 1012957, "mc": 54, "oc": 8}, {"id": 1013900, "mc": 1, "oc": 0}, {"id": 1014141, "mc": 777, "oc": 151}, {"id": 1018659, "mc": 231, "oc": 19}, {"id": 1019808, "mc": 23, "oc": 6}, {"id": 1020176, "mc": 12, "oc": 4}, {"id": 1020462, "mc": 41, "oc": 17}, {"id": 1021262, "mc": 1351, "oc": 48}, {"id": 1023858, "mc": 79, "oc": 18}, {"id": 1025427, "mc": 54, "oc": 7}, {"id": 1026301, "mc": 7122, "oc": 165}, {"id": 1026349, "mc": 4, "oc": 0}, {"id": 1028394, "mc": 7, "oc": 6}, {"id": 1028968, "mc": 11, "oc": 2}, {"id": 1029775, "mc": 33, "oc": 7}, {"id": 1029943, "mc": 28, "oc": 6}, {"id": 1030022, "mc": 1, "oc": 0}, {"id": 1030739, "mc": 2642, "oc": 31}, {"id": 1030937, "mc": 68, "oc": 19}, {"id": 1032131, "mc": 4, "oc": 0}, {"id": 1032340, "mc": 15, "oc": 4}, {"id": 1033522, "mc": 46, "oc": 4}, {"id": 1035429, "mc": 21, "oc": 2}, {"id": 1035437, "mc": 24, "oc": 9}, {"id": 1038058, "mc": 196, "oc": 18}, {"id": 1038079, "mc": 686, "oc": 43}, {"id": 1039673, "mc": 25, "oc": 8}, {"id": 1040631, "mc": 3720, "oc": 33}, {"id": 1041504, "mc": 38, "oc": 6}, {"id": 1042713, "mc": 3, "oc": 0}, {"id": 1044141, "mc": 30, "oc": 14}, {"id": 1044904, "mc": 367, "oc": 46}, {"id": 1046034, "mc": 147, "oc": 27}, {"id": 1047352, "mc": 75, "oc": 18}, {"id": 1048540, "mc": 19, "oc": 8}, {"id": 1049707, "mc": 21, "oc": 4}, {"id": 1049876, "mc": 125, "oc": 14}, {"id": 1050303, "mc": 19, "oc": 1}, {"id": 1050782, "mc": 2, "oc": 0}, {"id": 1055142, "mc": 62, "oc": 6}, {"id": 1055511, "mc": 61, "oc": 0}, {"id": 1057019, "mc": 38, "oc": 12}, {"id": 1057123, "mc": 55, "oc": 9}, {"id": 1059032, "mc": 730, "oc": 62}, {"id": 1060148, "mc": 1408, "oc": 18}, {"id": 1061263, "mc": 1594, "oc": 33}, {"id": 1061920, "mc": 511, "oc": 114}, {"id": 1065125, "mc": 2164, "oc": 201}, {"id": 1066778, "mc": 29, "oc": 3}, {"id": 1067044, "mc": 71, "oc": 2}, {"id": 1068056, "mc": 1525, "oc": 158}, {"id": 1068420, "mc": 30, "oc": 8}, {"id": 1069024, "mc": 7, "oc": 1}, {"id": 1069033, "mc": 9, "oc": 4}, {"id": 1070882, "mc": 1, "oc": 0}, {"id": 1070996, "mc": 22, "oc": 1}, {"id": 1071377, "mc": 48, "oc": 13}, {"id": 1071849, "mc": 74, "oc": 10}, {"id": 1073102, "mc": 23, "oc": 2}, {"id": 1074921, "mc": 2, "oc": 0}, {"id": 1075217, "mc": 11, "oc": 6}, {"id": 1076111, "mc": 801, "oc": 217}, {"id": 1076239, "mc": 3132, "oc": 5}, {"id": 1076480, "mc": 208, "oc": 64}, {"id": 1076502, "mc": 26, "oc": 3}, {"id": 1076742, "mc": 554, "oc": 17}, {"id": 1076822, "mc": 9, "oc": 5}, {"id": 1076830, "mc": 22, "oc": 13}, {"id": 1077780, "mc": 79, "oc": 7}, {"id": 1077950, "mc": 64, "oc": 12}, {"id": 1078034, "mc": 33, "oc": 6}, {"id": 1078667, "mc": 40, "oc": 7}, {"id": 1079748, "mc": 48, "oc": 14}, {"id": 1080402, "mc": 1, "oc": 0}, {"id": 1080849, "mc": 83, "oc": 3}, {"id": 1081032, "mc": 603, "oc": 30}, {"id": 1082133, "mc": 100, "oc": 7}, {"id": 1082630, "mc": 10, "oc": 7}, {"id": 1083393, "mc": 2087, "oc": 6}, {"id": 1084779, "mc": 18, "oc": 2}, {"id": 1086295, "mc": 48, "oc": 15}, {"id": 1087670, "mc": 256, "oc": 8}, {"id": 1088587, "mc": 75, "oc": 15}, {"id": 1088860, "mc": 1749, "oc": 103}, {"id": 1090772, "mc": 81, "oc": 4}, {"id": 1091455, "mc": 8, "oc": 0}, {"id": 1091546, "mc": 293, "oc": 10}, {"id": 1092696, "mc": 234, "oc": 15}, {"id": 1092864, "mc": 345, "oc": 36}, {"id": 1094218, "mc": 178, "oc": 29}, {"id": 1094661, "mc": 1012, "oc": 32}, {"id": 1095110, "mc": 31, "oc": 4}, {"id": 1095786, "mc": 80, "oc": 21}, {"id": 1095975, "mc": 24, "oc": 0}, {"id": 1098034, "mc": 53, "oc": 6}, {"id": 1098090, "mc": 24, "oc": 5}, {"id": 1101431, "mc": 154, "oc": 24}, {"id": 1101558, "mc": 24, "oc": 8}, {"id": 1102510, "mc": 31, "oc": 0}, {"id": 1103588, "mc": 88, "oc": 13}, {"id": 1105245, "mc": 155, "oc": 11}, {"id": 1105530, "mc": 50, "oc": 4}, {"id": 1105599, "mc": 22, "oc": 7}, {"id": 1106853, "mc": 915, "oc": 94}, {"id": 1107086, "mc": 24, "oc": 6}, {"id": 1109387, "mc": 30, "oc": 7}, {"id": 1110036, "mc": 29, "oc": 13}, {"id": 1110613, "mc": 38, "oc": 7}, {"id": 1111289, "mc": 5, "oc": 4}, {"id": 1111716, "mc": 37, "oc": 0}, {"id": 1111798, "mc": 161, "oc": 32}, {"id": 1111839, "mc": 14, "oc": 7}, {"id": 1111882, "mc": 288, "oc": 85}, {"id": 1112994, "mc": 3, "oc": 2}, {"id": 1113205, "mc": 51, "oc": 17}, {"id": 1114414, "mc": 38, "oc": 12}, {"id": 1115220, "mc": 77, "oc": 5}, {"id": 1116263, "mc": 450, "oc": 9}, {"id": 1116307, "mc": 5, "oc": 2}, {"id": 1116347, "mc": 5, "oc": 1}, {"id": 1116917, "mc": 4, "oc": 1}, {"id": 1117379, "mc": 244, "oc": 22}, {"id": 1117601, "mc": 2, "oc": 1}, {"id": 1118485, "mc": 5, "oc": 0}, {"id": 1119525, "mc": 77, "oc": 10}, {"id": 1119535, "mc": 399, "oc": 91}, {"id": 1119728, "mc": 35, "oc": 11}, {"id": 1120815, "mc": 17, "oc": 9}, {"id": 1122577, "mc": 36, "oc": 9}, {"id": 1123521, "mc": 673, "oc": 115}, {"id": 1124117, "mc": 148, "oc": 22}, {"id": 1124768, "mc": 50, "oc": 12}, {"id": 1125351, "mc": 443, "oc": 53}, {"id": 1125864, "mc": 1422, "oc": 252}, {"id": 1126081, "mc": 116, "oc": 3}, {"id": 1126850, "mc": 21, "oc": 4}, {"id": 1128094, "mc": 135, "oc": 16}, {"id": 1128966, "mc": 1432, "oc": 124}, {"id": 1129877, "mc": 20, "oc": 1}, {"id": 1130290, "mc": 20, "oc": 5}, {"id": 1130383, "mc": 84, "oc": 25}, {"id": 1133411, "mc": 17, "oc": 7}, {"id": 1133756, "mc": 438, "oc": 45}, {"id": 1134401, "mc": 41, "oc": 11}, {"id": 1134706, "mc": 16, "oc": 4}, {"id": 1135410, "mc": 23, "oc": 5}, {"id": 1136569, "mc": 15, "oc": 1}, {"id": 1137682, "mc": 14, "oc": 1}, {"id": 1138681, "mc": 16, "oc": 7}, {"id": 1141488, "mc": 26, "oc": 12}, {"id": 1141554, "mc": 21, "oc": 7}, {"id": 1141680, "mc": 14, "oc": 5}, {"id": 1142162, "mc": 680, "oc": 164}, {"id": 1146810, "mc": 53, "oc": 13}, {"id": 1147281, "mc": 224, "oc": 43}, {"id": 1147726, "mc": 3685, "oc": 113}, {"id": 1147817, "mc": 2076, "oc": 70}, {"id": 1148516, "mc": 126, "oc": 21}, {"id": 1148686, "mc": 214, "oc": 29}, {"id": 1149285, "mc": 32, "oc": 8}, {"id": 1150033, "mc": 79, "oc": 10}, {"id": 1150178, "mc": 44, "oc": 11}, {"id": 1150521, "mc": 453, "oc": 64}, {"id": 1151032, "mc": 123, "oc": 15}, {"id": 1151799, "mc": 649, "oc": 114}, {"id": 1152315, "mc": 34, "oc": 3}, {"id": 1153113, "mc": 26, "oc": 4}, {"id": 1155001, "mc": 47, "oc": 7}, {"id": 1156438, "mc": 1, "oc": 0}, {"id": 1156763, "mc": 69, "oc": 6}, {"id": 1157972, "mc": 35, "oc": 11}, {"id": 1158389, "mc": 11, "oc": 0}, {"id": 1158603, "mc": 16, "oc": 1}, {"id": 1160424, "mc": 840, "oc": 69}, {"id": 1160750, "mc": 2098, "oc": 7}, {"id": 1161201, "mc": 590, "oc": 68}, {"id": 1162365, "mc": 330, "oc": 35}, {"id": 1162385, "mc": 39, "oc": 7}, {"id": 1163204, "mc": 16, "oc": 3}, {"id": 1167816, "mc": 68, "oc": 14}, {"id": 1169047, "mc": 6, "oc": 2}, {"id": 1171032, "mc": 58, "oc": 9}, {"id": 1173822, "mc": 11, "oc": 2}, {"id": 1174818, "mc": 14, "oc": 2}, {"id": 1175116, "mc": 32, "oc": 11}, {"id": 1176312, "mc": 78, "oc": 13}, {"id": 1176459, "mc": 13716, "oc": 374}, {"id": 1178216, "mc": 279, "oc": 81}, {"id": 1180035, "mc": 112, "oc": 15}, {"id": 1180284, "mc": 797, "oc": 209}, {"id": 1180866, "mc": 110, "oc": 23}, {"id": 1181354, "mc": 73, "oc": 8}, {"id": 1184081, "mc": 142, "oc": 28}, {"id": 1184268, "mc": 134, "oc": 18}, {"id": 1184481, "mc": 121, "oc": 28}, {"id": 1186302, "mc": 57, "oc": 16}, {"id": 1186334, "mc": 52, "oc": 3}, {"id": 1186811, "mc": 695, "oc": 42}, {"id": 1187619, "mc": 114, "oc": 23}, {"id": 1189484, "mc": 30, "oc": 1}, {"id": 1190552, "mc": 25, "oc": 6}, {"id": 1192558, "mc": 73, "oc": 13}, {"id": 1194015, "mc": 14, "oc": 9}, {"id": 1194133, "mc": 99, "oc": 14}, {"id": 1194424, "mc": 213, "oc": 29}, {"id": 1195280, "mc": 37, "oc": 2}, {"id": 1195340, "mc": 70, "oc": 22}, {"id": 1197983, "mc": 238, "oc": 23}, {"id": 1199469, "mc": 132, "oc": 7}, {"id": 1201752, "mc": 73, "oc": 14}, {"id": 1202809, "mc": 9, "oc": 1}, {"id": 1203871, "mc": 10, "oc": 5}, {"id": 1204813, "mc": 3, "oc": 1}, {"id": 1206018, "mc": 24, "oc": 3}, {"id": 1206573, "mc": 57, "oc": 13}, {"id": 1207749, "mc": 24608, "oc": 390}, {"id": 1207810, "mc": 18, "oc": 4}, {"id": 1208605, "mc": 65, "oc": 10}, {"id": 1210071, "mc": 69, "oc": 21}, {"id": 1211486, "mc": 606, "oc": 169}, {"id": 1213033, "mc": 23, "oc": 2}, {"id": 1213259, "mc": 2690, "oc": 129}, {"id": 1214940, "mc": 30, "oc": 7}, {"id": 1215336, "mc": 4590, "oc": 856}, {"id": 1216100, "mc": 55, "oc": 6}, {"id": 1216299, "mc": 254, "oc": 34}, {"id": 1216702, "mc": 12, "oc": 5}, {"id": 1216905, "mc": 146, "oc": 25}, {"id": 1217313, "mc": 34, "oc": 12}, {"id": 1217792, "mc": 31, "oc": 10}, {"id": 1219112, "mc": 26, "oc": 10}, {"id": 1219470, "mc": 3, "oc": 1}, {"id": 1219955, "mc": 12, "oc": 0}, {"id": 1221433, "mc": 174, "oc": 29}, {"id": 1223897, "mc": 243, "oc": 18}, {"id": 1224146, "mc": 5, "oc": 0}, {"id": 1224253, "mc": 218, "oc": 20}, {"id": 1226303, "mc": 571, "oc": 55}, {"id": 1226529, "mc": 19, "oc": 9}, {"id": 1226539, "mc": 14, "oc": 4}, {"id": 1227044, "mc": 82, "oc": 11}, {"id": 1227491, "mc": 976, "oc": 80}, {"id": 1228328, "mc": 27, "oc": 3}, {"id": 1229511, "mc": 53, "oc": 6}, {"id": 1234594, "mc": 293, "oc": 36}, {"id": 1235457, "mc": 1, "oc": 0}, {"id": 1236026, "mc": 17, "oc": 2}, {"id": 1236040, "mc": 54, "oc": 13}, {"id": 1236658, "mc": 55, "oc": 13}, {"id": 1237889, "mc": 860, "oc": 75}, {"id": 1238348, "mc": 185, "oc": 27}, {"id": 1238677, "mc": 148, "oc": 31}, {"id": 1238750, "mc": 11, "oc": 6}, {"id": 1239367, "mc": 9, "oc": 1}, {"id": 1240561, "mc": 134, "oc": 16}, {"id": 1240817, "mc": 99, "oc": 32}, {"id": 1240860, "mc": 75, "oc": 21}, {"id": 1241293, "mc": 28, "oc": 11}, {"id": 1242027, "mc": 11, "oc": 5}, {"id": 1243092, "mc": 200, "oc": 17}, {"id": 1244541, "mc": 87, "oc": 11}, {"id": 1245955, "mc": 214, "oc": 17}, {"id": 1246316, "mc": 1099, "oc": 49}, {"id": 1247085, "mc": 24, "oc": 10}, {"id": 1248202, "mc": 32, "oc": 6}, {"id": 1249806, "mc": 321, "oc": 35}, {"id": 1249958, "mc": 220, "oc": 76}, {"id": 1249986, "mc": 215, "oc": 31}], "mrpupe": [{"id": 1000232, "mc": 152, "oc": 28}], "mrhootyhoot1": [{"id": 1000307, "mc": 210, "oc": 89}], "mrgreatnes": [{"id": 1000499, "mc": 74, "oc": 34}], "mrblackusiek": [{"id": 1000816, "mc": 131, "oc": 35}], "mrpresidentxxx": [{"id": 1001084, "mc": 35, "oc": 9}], "mrman3542": [{"id": 1001191, "mc": 15, "oc": 1}], "mrnasa": [{"id": 1001710, "mc": 538, "oc": 44}], "mrrnkrblx": [{"id": 1002428, "mc": 126, "oc": 20}], "mrbik225": [{"id": 1002495, "mc": 1, "oc": 0}], "mrdiddler1": [{"id": 1002919, "mc": 1, "oc": 0}], "mrsnoogle": [{"id": 1004163, "mc": 48, "oc": 3}], "mrrenegade": [{"id": 1004188, "mc": 117, "oc": 27}], "mrfudgemonkeyz": [{"id": 1004447, "mc": 6002, "oc": 709}], "mrrevengerx": [{"id": 1004877, "mc": 159, "oc": 15}], "mrxn1": [{"id": 1004908, "mc": 214, "oc": 50}], "mryani": [{"id": 1004935, "mc": 10, "oc": 3}], "mrbrucealmighty3186": [{"id": 1005325, "mc": 39, "oc": 8}], "mrinfinity1495yt4594": [{"id": 1005385, "mc": 45, "oc": 8}], "mrkooki": [{"id": 1005592, "mc": 298, "oc": 41}], "mrdragon240": [{"id": 1005618, "mc": 91, "oc": 11}], "mrderp6123": [{"id": 1006134, "mc": 4, "oc": 1}], "mrbump": [{"id": 1006266, "mc": 33, "oc": 3}], "mrwombat0001": [{"id": 1006725, "mc": 109, "oc": 42}], "mrcowboy0264": [{"id": 1007593, "mc": 3, "oc": 0}], "mrcab55": [{"id": 1007625, "mc": 30, "oc": 15}], "mrjaroslavik": [{"id": 1007834, "mc": 102, "oc": 25}], "mrsir71": [{"id": 1008018, "mc": 72, "oc": 22}, {"id": 1240546, "mc": 261, "oc": 79}], "mrjesoo": [{"id": 1008189, "mc": 47, "oc": 9}], "mrdarrengriffin": [{"id": 1008574, "mc": 25, "oc": 6}], "mrod9065": [{"id": 1008778, "mc": 115, "oc": 3}], "mrdittofazzy": [{"id": 1008828, "mc": 52, "oc": 8}], "mrovd": [{"id": 1009247, "mc": 381, "oc": 83}], "mrblake213": [{"id": 1009288, "mc": 3154, "oc": 606}], "mrteetom": [{"id": 1010247, "mc": 43, "oc": 4}], "mrcatplayz6048": [{"id": 1010354, "mc": 1, "oc": 0}], "mrmcgriddle9774": [{"id": 1010471, "mc": 2, "oc": 0}], "mrltrader": [{"id": 1010715, "mc": 58, "oc": 0}], "mrwalkindolo": [{"id": 1010978, "mc": 196, "oc": 7}], "mrbigbizznes": [{"id": 1011505, "mc": 229, "oc": 44}], "mrvegit": [{"id": 1012611, "mc": 33, "oc": 1}], "mrsneakz": [{"id": 1012715, "mc": 240, "oc": 83}], "mrnezie": [{"id": 1012811, "mc": 489, "oc": 42}], "mrclean0993": [{"id": 1012988, "mc": 124, "oc": 24}], "mrbazat": [{"id": 1013031, "mc": 49, "oc": 7}], "mrshawn": [{"id": 1013287, "mc": 256, "oc": 83}], "mrmaskk": [{"id": 1013616, "mc": 98, "oc": 31}], "mrxfactor": [{"id": 1013962, "mc": 964, "oc": 89}], "mrsid": [{"id": 1013989, "mc": 6, "oc": 1}], "mrgreg": [{"id": 1014010, "mc": 8000, "oc": 2349}], "mrsnoof": [{"id": 1014261, "mc": 50, "oc": 12}], "mrdomian": [{"id": 1014415, "mc": 5465, "oc": 1283}], "mrflamey": [{"id": 1014986, "mc": 22, "oc": 8}], "mrqu": [{"id": 1015260, "mc": 141, "oc": 18}], "mrtriple": [{"id": 1015509, "mc": 1, "oc": 0}], "mrdevil101": [{"id": 1015804, "mc": 1926, "oc": 194}], "mrnjaovac": [{"id": 1016391, "mc": 16, "oc": 5}], "mrlenti": [{"id": 1016483, "mc": 7, "oc": 3}], "mrd": [{"id": 1016706, "mc": 5, "oc": 1}], "mracni4476": [{"id": 1016796, "mc": 1, "oc": 0}], "mrdark7602": [{"id": 1017138, "mc": 1371, "oc": 117}], "mrsremi": [{"id": 1017435, "mc": 157, "oc": 65}], "mrworldwide4707": [{"id": 1017554, "mc": 6, "oc": 0}], "mralerderp": [{"id": 1017577, "mc": 55, "oc": 24}], "mrkumar": [{"id": 1017650, "mc": 201, "oc": 21}], "mrmicky": [{"id": 1017807, "mc": 3342, "oc": 1063}], "mrleo1998": [{"id": 1017907, "mc": 809, "oc": 50}], "mrkuchi": [{"id": 1018413, "mc": 1050, "oc": 220}], "mrsetting": [{"id": 1018641, "mc": 13, "oc": 8}, {"id": 1243711, "mc": 4, "oc": 3}], "mryonko": [{"id": 1019667, "mc": 27, "oc": 3}], "mrmattimation": [{"id": 1019733, "mc": 4, "oc": 1}, {"id": 1179892, "mc": 78, "oc": 9}], "mrjammermusic": [{"id": 1019921, "mc": 358, "oc": 10}], "mrliam2614": [{"id": 1020051, "mc": 6, "oc": 1}], "mrbumban1": [{"id": 1021121, "mc": 295, "oc": 70}], "mrmanuportu": [{"id": 1021231, "mc": 31, "oc": 1}], "mrgladdy": [{"id": 1021281, "mc": 73, "oc": 20}], "mrvickie": [{"id": 1021689, "mc": 2, "oc": 0}], "mrmysteriu": [{"id": 1021784, "mc": 195, "oc": 70}], "mrajr": [{"id": 1021798, "mc": 122, "oc": 39}], "mrhayda": [{"id": 1021913, "mc": 4840, "oc": 200}, {"id": 1179959, "mc": 1141, "oc": 44}], "mrgrzesik": [{"id": 1022092, "mc": 153, "oc": 23}], "mrjohn6774": [{"id": 1022697, "mc": 258, "oc": 38}], "mrtttn": [{"id": 1022734, "mc": 327, "oc": 14}], "mrlampy": [{"id": 1022996, "mc": 2, "oc": 0}], "mraugu9016": [{"id": 1023377, "mc": 15, "oc": 5}], "mrjonhudson": [{"id": 1023545, "mc": 20, "oc": 2}], "mrkacu13": [{"id": 1024132, "mc": 21, "oc": 8}], "mrteevee": [{"id": 1024406, "mc": 22, "oc": 4}], "mrmetaspycnft0664": [{"id": 1024449, "mc": 38, "oc": 6}], "mreurojima": [{"id": 1024657, "mc": 5, "oc": 4}], "mrjerkyjerky": [{"id": 1024940, "mc": 42, "oc": 20}], "mrprotector": [{"id": 1025571, "mc": 52, "oc": 17}], "mrcyjanek": [{"id": 1025651, "mc": 8, "oc": 2}], "mrskiman": [{"id": 1025721, "mc": 35, "oc": 10}], "mrlightsun": [{"id": 1025958, "mc": 6, "oc": 3}], "mrsilentz": [{"id": 1025961, "mc": 141, "oc": 8}], "mrarnaud": [{"id": 1025969, "mc": 981, "oc": 47}, {"id": 1240536, "mc": 35, "oc": 11}], "mrkimkimora": [{"id": 1026612, "mc": 214, "oc": 61}], "mrshallow": [{"id": 1026949, "mc": 24, "oc": 7}], "mrrquinny": [{"id": 1027046, "mc": 132, "oc": 45}], "mrdeficient": [{"id": 1027069, "mc": 7, "oc": 1}], "mrtoptick": [{"id": 1028190, "mc": 972, "oc": 340}], "mrs": [{"id": 1028256, "mc": 74, "oc": 3}, {"id": 1064728, "mc": 94, "oc": 7}, {"id": 1109671, "mc": 238, "oc": 29}, {"id": 1147031, "mc": 44, "oc": 3}, {"id": 1174844, "mc": 821, "oc": 134}, {"id": 1203507, "mc": 23, "oc": 5}, {"id": 1220351, "mc": 64, "oc": 11}, {"id": 1225993, "mc": 29, "oc": 5}], "mrroidley": [{"id": 1028519, "mc": 1, "oc": 0}], "mr27unbreakable": [{"id": 1028780, "mc": 71, "oc": 7}], "mrkob7114": [{"id": 1028879, "mc": 3, "oc": 2}], "mrscauthd": [{"id": 1029130, "mc": 2141, "oc": 601}], "mrwolfsergio6663": [{"id": 1029887, "mc": 683, "oc": 17}], "mrhartmann": [{"id": 1029917, "mc": 2197, "oc": 11}], "mrsolodoughlow": [{"id": 1030043, "mc": 97, "oc": 25}], "mrzandtman": [{"id": 1030888, "mc": 127, "oc": 22}], "mrsalwayswright": [{"id": 1031357, "mc": 33, "oc": 6}], "mrcreatifee": [{"id": 1031421, "mc": 3431, "oc": 69}], "mrgreenrain6533": [{"id": 1031435, "mc": 1, "oc": 0}], "mrthe1badman": [{"id": 1032724, "mc": 127, "oc": 12}], "mriceflame": [{"id": 1032790, "mc": 335, "oc": 21}], "mrmxyzptik": [{"id": 1032947, "mc": 51, "oc": 8}], "mrthinger": [{"id": 1033136, "mc": 2522, "oc": 642}], "mrwenter": [{"id": 1033569, "mc": 182, "oc": 15}], "mrbryonyt": [{"id": 1033670, "mc": 2, "oc": 0}], "mrdinklepus": [{"id": 1033762, "mc": 559, "oc": 172}], "mrzakaria": [{"id": 1034930, "mc": 1, "oc": 0}], "mrstephen": [{"id": 1035061, "mc": 681, "oc": 234}], "mrginn": [{"id": 1035156, "mc": 37, "oc": 13}], "mrudd": [{"id": 1035309, "mc": 17, "oc": 3}], "mrcase": [{"id": 1035424, "mc": 802, "oc": 44}], "mrboom": [{"id": 1035441, "mc": 42, "oc": 5}], "mrgameboiyt": [{"id": 1035472, "mc": 9, "oc": 0}], "mrkill": [{"id": 1035670, "mc": 46, "oc": 14}], "mrmajikku": [{"id": 1036301, "mc": 173, "oc": 62}], "mrseem": [{"id": 1036402, "mc": 26, "oc": 7}], "mrcrabspizza": [{"id": 1037183, "mc": 3338, "oc": 124}], "mrblue575": [{"id": 1037621, "mc": 877, "oc": 390}], "mrvedakkan": [{"id": 1037939, "mc": 2673, "oc": 13}], "mrdozor": [{"id": 1038065, "mc": 44, "oc": 0}], "mrraxou": [{"id": 1038416, "mc": 2, "oc": 0}], "mrbudzo": [{"id": 1038500, "mc": 84, "oc": 14}], "mrtalente": [{"id": 1038625, "mc": 16483, "oc": 516}], "mrskally": [{"id": 1038646, "mc": 33, "oc": 15}], "mrjake8077": [{"id": 1038997, "mc": 71, "oc": 12}], "mrayomakqueen333": [{"id": 1039539, "mc": 31, "oc": 12}], "mr1vgy": [{"id": 1039945, "mc": 8, "oc": 0}], "mrdosa": [{"id": 1040229, "mc": 54, "oc": 17}], "mrlezofffire123": [{"id": 1040403, "mc": 34, "oc": 10}], "mrloraz": [{"id": 1040911, "mc": 199, "oc": 32}], "mrscottypieey5670": [{"id": 1040977, "mc": 8, "oc": 3}], "mrkarton": [{"id": 1041570, "mc": 17, "oc": 2}], "mrslicksalot": [{"id": 1041741, "mc": 16, "oc": 4}], "mrt": [{"id": 1041891, "mc": 35, "oc": 8}], "mrsstick": [{"id": 1042611, "mc": 1789, "oc": 29}], "mrkomem": [{"id": 1042795, "mc": 767, "oc": 122}], "mruvinshteyntriumph": [{"id": 1043551, "mc": 22, "oc": 0}], "mrsveilmont": [{"id": 1043705, "mc": 24, "oc": 16}], "mrod08": [{"id": 1043726, "mc": 8, "oc": 3}], "mrhellaz": [{"id": 1045066, "mc": 8, "oc": 0}], "mraugmented": [{"id": 1045280, "mc": 175, "oc": 17}], "mrbradprime": [{"id": 1045677, "mc": 81, "oc": 13}], "mrktospl": [{"id": 1045797, "mc": 54, "oc": 17}], "mralv4ro": [{"id": 1046256, "mc": 7, "oc": 3}], "mrboglet": [{"id": 1046466, "mc": 68, "oc": 3}], "mraft": [{"id": 1046681, "mc": 172, "oc": 40}], "mrvalentine710": [{"id": 1046687, "mc": 96, "oc": 23}], "mrgjostgamin": [{"id": 1046717, "mc": 1, "oc": 0}], "mrpekka16": [{"id": 1047554, "mc": 46, "oc": 6}], "mrakovey": [{"id": 1047589, "mc": 289, "oc": 48}], "mrxeliu": [{"id": 1047820, "mc": 35, "oc": 9}], "mra03750": [{"id": 1047882, "mc": 1, "oc": 0}], "mr96": [{"id": 1048047, "mc": 31, "oc": 4}], "mrthatamericangamer": [{"id": 1048282, "mc": 57, "oc": 26}], "mrkishi": [{"id": 1048326, "mc": 1050, "oc": 40}], "mrwingaming": [{"id": 1048661, "mc": 262, "oc": 15}], "mraardappel": [{"id": 1048759, "mc": 350, "oc": 73}], "mrcupcake86": [{"id": 1048912, "mc": 1202, "oc": 53}], "mrfennec1993": [{"id": 1049158, "mc": 3, "oc": 0}], "mrjv": [{"id": 1049262, "mc": 16, "oc": 3}], "mrwilmar99": [{"id": 1049422, "mc": 30, "oc": 8}], "mrmillennial": [{"id": 1049481, "mc": 115, "oc": 20}], "mrunbekannt81": [{"id": 1049665, "mc": 48, "oc": 12}], "mrkapao": [{"id": 1049745, "mc": 66, "oc": 15}], "mrfancy25": [{"id": 1049781, "mc": 4, "oc": 2}], "mrnice8930": [{"id": 1049978, "mc": 7, "oc": 3}], "mrgrenat": [{"id": 1050345, "mc": 24, "oc": 4}], "mrrichardbet": [{"id": 1050371, "mc": 21, "oc": 1}], "mrjducky": [{"id": 1050419, "mc": 101, "oc": 36}], "mrcat10110101010": [{"id": 1050608, "mc": 28, "oc": 4}], "mrpoisontaco": [{"id": 1050624, "mc": 14, "oc": 4}], "mrflopa": [{"id": 1051220, "mc": 24, "oc": 7}], "mrssoul": [{"id": 1051677, "mc": 2, "oc": 1}], "mrcat": [{"id": 1051880, "mc": 660, "oc": 114}], "mrman1500": [{"id": 1051905, "mc": 34, "oc": 10}], "mrintangble": [{"id": 1052084, "mc": 102, "oc": 7}], "mrithunzana9458": [{"id": 1052109, "mc": 17, "oc": 9}], "mrelessea": [{"id": 1052377, "mc": 31, "oc": 11}], "mrraggaq": [{"id": 1052642, "mc": 5, "oc": 1}], "mrph4nt0m": [{"id": 1052678, "mc": 773, "oc": 73}], "mrsalizz": [{"id": 1052726, "mc": 9, "oc": 1}], "mrthelode": [{"id": 1052882, "mc": 70, "oc": 12}], "mrgplay": [{"id": 1053166, "mc": 1358, "oc": 260}], "mrlegend8957": [{"id": 1053462, "mc": 8, "oc": 5}], "mrfrogsnut": [{"id": 1053789, "mc": 15, "oc": 1}], "mrgatodiablo": [{"id": 1053847, "mc": 12, "oc": 2}], "mrwinterbottom": [{"id": 1055241, "mc": 13, "oc": 0}], "mrdawnandrew": [{"id": 1055411, "mc": 60, "oc": 6}], "mrmonth24": [{"id": 1055755, "mc": 72, "oc": 16}], "mrstockmarket": [{"id": 1055863, "mc": 15, "oc": 1}], "mrozek": [{"id": 1056256, "mc": 1150, "oc": 32}], "mrwhxpz": [{"id": 1056285, "mc": 9, "oc": 7}, {"id": 1095359, "mc": 15, "oc": 7}], "mrcow": [{"id": 1056350, "mc": 965, "oc": 419}], "mrpurr": [{"id": 1056442, "mc": 6, "oc": 4}], "mrlegendaddy": [{"id": 1057047, "mc": 11, "oc": 3}], "mrwearily": [{"id": 1057288, "mc": 22, "oc": 10}], "mrzorki2443": [{"id": 1057638, "mc": 16, "oc": 0}], "mrslavictv": [{"id": 1059355, "mc": 120, "oc": 6}], "mrgcoin8984": [{"id": 1059871, "mc": 4, "oc": 0}], "mrzodiacbe": [{"id": 1059962, "mc": 2, "oc": 0}], "mrleaugan": [{"id": 1060283, "mc": 231, "oc": 51}], "mrsknowitall": [{"id": 1060347, "mc": 1232, "oc": 338}], "mrskeksii": [{"id": 1060919, "mc": 65, "oc": 15}], "mrclubpro": [{"id": 1061180, "mc": 18, "oc": 2}], "mrthp": [{"id": 1061536, "mc": 14, "oc": 6}], "mrsalmon523": [{"id": 1061762, "mc": 8, "oc": 6}], "mrmnek": [{"id": 1061899, "mc": 61, "oc": 5}], "mrsfungle": [{"id": 1061928, "mc": 14, "oc": 6}], "mrtngg": [{"id": 1062141, "mc": 159, "oc": 9}], "mrdrmufn": [{"id": 1063289, "mc": 13, "oc": 4}], "mrcoffeetv": [{"id": 1063330, "mc": 2815, "oc": 232}], "mranarcade": [{"id": 1063747, "mc": 99, "oc": 31}], "mrcako": [{"id": 1064246, "mc": 10207, "oc": 1336}], "mrfrank": [{"id": 1065287, "mc": 70, "oc": 13}], "mrblond": [{"id": 1065336, "mc": 42, "oc": 7}], "mrjpstilt": [{"id": 1065520, "mc": 57, "oc": 22}], "mrhieff": [{"id": 1065573, "mc": 7, "oc": 5}], "mrmuco": [{"id": 1066161, "mc": 65, "oc": 6}], "mrlionyt": [{"id": 1066215, "mc": 2, "oc": 1}], "mrboost": [{"id": 1066273, "mc": 346, "oc": 137}], "mrjack0429": [{"id": 1066313, "mc": 432, "oc": 9}], "mrbamason": [{"id": 1066654, "mc": 81, "oc": 16}], "mrwizard": [{"id": 1066891, "mc": 700, "oc": 8}], "mrkiou": [{"id": 1066999, "mc": 101, "oc": 13}], "mrsatan0666": [{"id": 1067097, "mc": 19, "oc": 3}], "mrtwister23": [{"id": 1067240, "mc": 27, "oc": 6}], "mricog": [{"id": 1067793, "mc": 2, "oc": 0}], "mrsnite5454": [{"id": 1067833, "mc": 1237, "oc": 30}], "mrgusfring": [{"id": 1067837, "mc": 4, "oc": 3}], "mrpirate6819": [{"id": 1068080, "mc": 21, "oc": 1}], "mrnebe": [{"id": 1068458, "mc": 84, "oc": 10}], "mrdick3184": [{"id": 1068526, "mc": 25, "oc": 7}], "mrterse": [{"id": 1068556, "mc": 10, "oc": 3}], "mrborsch5116": [{"id": 1068660, "mc": 1, "oc": 0}], "mr42": [{"id": 1068672, "mc": 9, "oc": 2}], "mrkzmsk": [{"id": 1069288, "mc": 57, "oc": 2}], "mrdoom": [{"id": 1069409, "mc": 40, "oc": 5}], "mrzinych": [{"id": 1069498, "mc": 169, "oc": 7}], "mrsbruhaha": [{"id": 1069670, "mc": 24, "oc": 3}], "mriolady": [{"id": 1069774, "mc": 1113, "oc": 9}], "mrchrishell": [{"id": 1070125, "mc": 86, "oc": 1}], "mrc2rule": [{"id": 1070654, "mc": 35, "oc": 4}], "mrdeniska1234": [{"id": 1070836, "mc": 64, "oc": 2}], "mrparpaing": [{"id": 1071071, "mc": 259, "oc": 30}], "mrbiffy": [{"id": 1071322, "mc": 15, "oc": 2}], "mrlarion": [{"id": 1071398, "mc": 81, "oc": 17}], "mrchickenwang": [{"id": 1071414, "mc": 526, "oc": 63}], "mrchocholate": [{"id": 1071697, "mc": 73, "oc": 12}], "mrdeliveryman": [{"id": 1071838, "mc": 726, "oc": 68}], "mrvuci": [{"id": 1072223, "mc": 46, "oc": 8}], "mrking5494": [{"id": 1072331, "mc": 112, "oc": 12}], "mrdrdk": [{"id": 1072471, "mc": 10, "oc": 0}], "mrxdreams54": [{"id": 1072480, "mc": 56, "oc": 8}], "mrking1234": [{"id": 1072804, "mc": 10, "oc": 4}], "mrblackmanboii3291": [{"id": 1073571, "mc": 2, "oc": 1}], "mrdweel": [{"id": 1073806, "mc": 115, "oc": 6}], "mryqhqysry0655": [{"id": 1073846, "mc": 16, "oc": 3}], "mrbnking": [{"id": 1074645, "mc": 470, "oc": 76}], "mrrootlog": [{"id": 1074975, "mc": 405, "oc": 13}], "mrbanjoozie": [{"id": 1075063, "mc": 50, "oc": 7}], "mrgit": [{"id": 1075162, "mc": 774, "oc": 72}], "mrgore84": [{"id": 1075231, "mc": 67, "oc": 7}], "mrclean4056": [{"id": 1075562, "mc": 64, "oc": 5}], "mrfernix": [{"id": 1075900, "mc": 7, "oc": 4}], "mrbexsi": [{"id": 1076353, "mc": 1164, "oc": 174}], "mrbr1ghtsid3": [{"id": 1076574, "mc": 52, "oc": 11}], "mrlordgarbage": [{"id": 1076629, "mc": 25, "oc": 9}], "mrmontanadk": [{"id": 1076776, "mc": 84, "oc": 25}], "mrgenx": [{"id": 1076855, "mc": 31, "oc": 1}], "mrbigbrainthe2nd": [{"id": 1077831, "mc": 20, "oc": 4}], "mrfun01": [{"id": 1077899, "mc": 485, "oc": 172}], "mrrichard999": [{"id": 1078108, "mc": 97, "oc": 19}], "mrcharm3403": [{"id": 1078157, "mc": 233, "oc": 4}], "mrbadim": [{"id": 1078165, "mc": 5, "oc": 1}], "mrcontext": [{"id": 1078366, "mc": 9, "oc": 1}], "mrwiz6rd": [{"id": 1078450, "mc": 19, "oc": 1}], "mrneoiss": [{"id": 1078607, "mc": 121, "oc": 15}], "mrmojito": [{"id": 1078670, "mc": 352, "oc": 82}], "mrsllante": [{"id": 1078843, "mc": 53, "oc": 22}], "mrnight1009": [{"id": 1078849, "mc": 74, "oc": 11}], "mrjiggles4057": [{"id": 1078946, "mc": 32, "oc": 2}], "mrmaclaster": [{"id": 1079070, "mc": 46, "oc": 7}], "mrtbgz": [{"id": 1079162, "mc": 2, "oc": 0}], "mrcryptoph": [{"id": 1079262, "mc": 52, "oc": 5}], "mrc0d3r": [{"id": 1079319, "mc": 164, "oc": 50}], "mrjangle": [{"id": 1079697, "mc": 17, "oc": 5}], "mrjosesitoh": [{"id": 1079935, "mc": 34, "oc": 12}], "mrarbenz": [{"id": 1080479, "mc": 18, "oc": 2}], "mrcrewwofficiel": [{"id": 1080741, "mc": 5, "oc": 1}], "mrxteam": [{"id": 1080745, "mc": 37, "oc": 2}], "mrdinlac": [{"id": 1080880, "mc": 12, "oc": 4}], "mrsvio": [{"id": 1080986, "mc": 74, "oc": 9}], "mrjocrafter": [{"id": 1081140, "mc": 7, "oc": 2}], "mrntou": [{"id": 1081330, "mc": 6, "oc": 1}], "mrc2785": [{"id": 1081502, "mc": 304, "oc": 5}], "mrzealot": [{"id": 1081749, "mc": 41, "oc": 2}], "mrwexfx": [{"id": 1082663, "mc": 17, "oc": 0}], "mrghost917": [{"id": 1082833, "mc": 198, "oc": 27}], "mrkew": [{"id": 1083382, "mc": 146, "oc": 14}], "mrbear7189": [{"id": 1083413, "mc": 1040, "oc": 88}], "mrkataboy": [{"id": 1083937, "mc": 36, "oc": 13}], "mrpolar": [{"id": 1084191, "mc": 446, "oc": 9}], "mrpepeog": [{"id": 1084394, "mc": 6, "oc": 3}], "mrfiliper": [{"id": 1084513, "mc": 5, "oc": 0}], "mrsbuzzy": [{"id": 1086149, "mc": 172, "oc": 58}], "mrjustin585": [{"id": 1086566, "mc": 83, "oc": 26}], "mrfinnerz": [{"id": 1086768, "mc": 21, "oc": 4}], "mrquechop": [{"id": 1086975, "mc": 2281, "oc": 179}], "mrmfretwell": [{"id": 1087431, "mc": 38, "oc": 12}], "mrdiegui": [{"id": 1088111, "mc": 112, "oc": 11}], "mrsfwogle": [{"id": 1088794, "mc": 55, "oc": 18}], "mrnemo0000": [{"id": 1088947, "mc": 231, "oc": 7}], "mrdandy": [{"id": 1089089, "mc": 147, "oc": 24}], "mrunderhill4707": [{"id": 1090477, "mc": 51, "oc": 15}], "mrtherm": [{"id": 1090484, "mc": 40, "oc": 11}], "mrmango": [{"id": 1090556, "mc": 1, "oc": 1}], "mreaqz": [{"id": 1090804, "mc": 452, "oc": 104}], "mrblue": [{"id": 1090982, "mc": 2466, "oc": 362}, {"id": 1140099, "mc": 14657, "oc": 3539}], "mrgalaxystar0824": [{"id": 1091056, "mc": 6, "oc": 1}], "mrduckisonline": [{"id": 1091159, "mc": 33, "oc": 9}], "mrfantuv": [{"id": 1091337, "mc": 365, "oc": 74}], "mrbuy": [{"id": 1091709, "mc": 2, "oc": 0}], "mrk9813": [{"id": 1091753, "mc": 34, "oc": 7}, {"id": 1195109, "mc": 79, "oc": 16}], "mrlt15": [{"id": 1091774, "mc": 133, "oc": 9}], "mrsepta": [{"id": 1092178, "mc": 17, "oc": 4}, {"id": 1155577, "mc": 8, "oc": 2}], "mremi": [{"id": 1092195, "mc": 70, "oc": 7}], "mr123j": [{"id": 1092301, "mc": 48, "oc": 4}], "mrrevo3d": [{"id": 1092665, "mc": 1679, "oc": 329}], "mrcrazyyyy": [{"id": 1092991, "mc": 15, "oc": 2}], "mrbpm96": [{"id": 1093348, "mc": 51, "oc": 6}], "mrkewoo": [{"id": 1093560, "mc": 6, "oc": 4}], "mrdemsu": [{"id": 1093745, "mc": 14, "oc": 5}], "mrbloodrune": [{"id": 1093926, "mc": 115, "oc": 17}], "mreternal": [{"id": 1094193, "mc": 2, "oc": 1}], "mrevilclown28": [{"id": 1094438, "mc": 25, "oc": 3}], "mrwildenfree": [{"id": 1094579, "mc": 55, "oc": 6}], "mrsahil5441": [{"id": 1094581, "mc": 43, "oc": 4}], "mrfelix906": [{"id": 1094593, "mc": 89, "oc": 20}], "mrscruffy": [{"id": 1094999, "mc": 158, "oc": 15}], "mrmike9527": [{"id": 1095262, "mc": 1804, "oc": 13}], "mrblooke": [{"id": 1095412, "mc": 234, "oc": 2}], "mrvalaudio": [{"id": 1095641, "mc": 155, "oc": 14}], "mrterrobyte": [{"id": 1095824, "mc": 95, "oc": 1}], "mrowcia": [{"id": 1095882, "mc": 86, "oc": 30}], "mremax": [{"id": 1096279, "mc": 115, "oc": 20}], "mrmurphy": [{"id": 1096395, "mc": 30, "oc": 5}], "mrpersonsmile": [{"id": 1096772, "mc": 44, "oc": 14}], "mrpemmfub": [{"id": 1096817, "mc": 871, "oc": 45}], "mrqasper": [{"id": 1096964, "mc": 50, "oc": 16}], "mrdouglax": [{"id": 1097153, "mc": 69, "oc": 9}], "mrbomman": [{"id": 1097435, "mc": 43, "oc": 12}], "mrbotman": [{"id": 1097576, "mc": 324, "oc": 23}], "mrmatalo": [{"id": 1097615, "mc": 25, "oc": 9}], "mrmarcusgd": [{"id": 1097888, "mc": 121, "oc": 21}, {"id": 1145847, "mc": 79, "oc": 18}], "mrsheen": [{"id": 1097944, "mc": 52, "oc": 13}], "mrkinn": [{"id": 1098155, "mc": 1072, "oc": 75}, {"id": 1124841, "mc": 905, "oc": 50}], "mrpigtipster": [{"id": 1098234, "mc": 39, "oc": 6}], "mrlegendpanda": [{"id": 1098487, "mc": 157, "oc": 23}], "mrbeast05341": [{"id": 1098942, "mc": 2, "oc": 0}], "mrfrump": [{"id": 1099169, "mc": 307, "oc": 33}], "mrcasual": [{"id": 1099256, "mc": 1057, "oc": 54}], "mrwek": [{"id": 1099863, "mc": 16, "oc": 5}], "mrcyjanek8985": [{"id": 1100161, "mc": 15, "oc": 0}], "mrmettwurscht": [{"id": 1100562, "mc": 54, "oc": 10}], "mrweissyyy": [{"id": 1101166, "mc": 18, "oc": 7}], "mrniceguy6709": [{"id": 1101354, "mc": 4, "oc": 0}], "mrfurkan": [{"id": 1101422, "mc": 75, "oc": 16}], "mrbored1": [{"id": 1101587, "mc": 41, "oc": 12}], "mrkoiru": [{"id": 1101638, "mc": 688, "oc": 59}], "mrdarling": [{"id": 1102279, "mc": 20, "oc": 1}], "mrcrullerboi": [{"id": 1102441, "mc": 18, "oc": 6}], "mrlestik": [{"id": 1102958, "mc": 78, "oc": 12}], "mrabcc": [{"id": 1103300, "mc": 465, "oc": 27}], "mraugu": [{"id": 1103346, "mc": 133, "oc": 16}, {"id": 1115955, "mc": 35, "oc": 8}], "mraweshum": [{"id": 1103772, "mc": 65, "oc": 3}], "mrsnuggles01": [{"id": 1103888, "mc": 1398, "oc": 9}], "mraksoll": [{"id": 1104092, "mc": 533, "oc": 52}], "mrtz": [{"id": 1104448, "mc": 505, "oc": 61}], "mrsclutch": [{"id": 1104511, "mc": 28, "oc": 8}], "mrurbxn": [{"id": 1104771, "mc": 74, "oc": 9}], "mrogz": [{"id": 1104828, "mc": 1135, "oc": 118}], "mrgangreen": [{"id": 1105739, "mc": 95, "oc": 30}], "mrmanhd": [{"id": 1106397, "mc": 47, "oc": 5}], "mrhappy5878": [{"id": 1106778, "mc": 13, "oc": 5}], "mrpowergamerbr": [{"id": 1106949, "mc": 71, "oc": 3}], "mraipom": [{"id": 1107415, "mc": 102, "oc": 15}], "mra007": [{"id": 1107503, "mc": 26, "oc": 3}], "mrcherif": [{"id": 1107805, "mc": 2661, "oc": 279}], "mrxime": [{"id": 1108085, "mc": 40, "oc": 6}], "mralexnui": [{"id": 1108274, "mc": 34, "oc": 11}], "mrpota70h3ad": [{"id": 1108654, "mc": 28, "oc": 8}], "mrmarx5515": [{"id": 1108757, "mc": 103, "oc": 7}], "mrartbrain": [{"id": 1108839, "mc": 76, "oc": 5}], "mrmuratovic": [{"id": 1109246, "mc": 2090, "oc": 132}], "mrtroopy": [{"id": 1109270, "mc": 49, "oc": 9}], "mrmrmtrp9": [{"id": 1109453, "mc": 27, "oc": 6}], "mrwiggly3403": [{"id": 1109765, "mc": 67, "oc": 8}], "mralx": [{"id": 1109771, "mc": 38, "oc": 9}], "mrlight2306": [{"id": 1110142, "mc": 181, "oc": 24}], "mrg9403": [{"id": 1110633, "mc": 198, "oc": 19}], "mrmorsateve": [{"id": 1110879, "mc": 5, "oc": 1}], "mrready": [{"id": 1110892, "mc": 264, "oc": 39}], "mrknight": [{"id": 1110924, "mc": 37, "oc": 6}], "mrjskulloz": [{"id": 1111329, "mc": 1889, "oc": 123}], "mrkrzychumix": [{"id": 1111415, "mc": 453, "oc": 73}], "mrwaite": [{"id": 1111580, "mc": 46, "oc": 8}], "mrhansome8037": [{"id": 1111662, "mc": 1, "oc": 0}], "mroutcast": [{"id": 1111759, "mc": 61, "oc": 14}], "mrkwnzl": [{"id": 1112101, "mc": 155, "oc": 59}], "mrvlbro": [{"id": 1112438, "mc": 157, "oc": 17}], "mrmorden1141": [{"id": 1113527, "mc": 116, "oc": 8}], "mrthegamer2": [{"id": 1113698, "mc": 12, "oc": 5}], "mrgloom": [{"id": 1113817, "mc": 7, "oc": 1}], "mrh4tz": [{"id": 1114144, "mc": 13, "oc": 5}], "mrvastayan": [{"id": 1114320, "mc": 9498, "oc": 1803}], "mrarq": [{"id": 1114776, "mc": 97, "oc": 21}], "mrnecron": [{"id": 1114791, "mc": 53, "oc": 18}], "mrzainplaysalt4244": [{"id": 1114861, "mc": 56, "oc": 15}], "mryellowheart": [{"id": 1115080, "mc": 1114, "oc": 64}], "mrschneebly": [{"id": 1115101, "mc": 74, "oc": 6}], "mrbate": [{"id": 1115320, "mc": 116, "oc": 13}], "mrbom": [{"id": 1115566, "mc": 565, "oc": 28}], "mrgentlezombie": [{"id": 1115593, "mc": 8, "oc": 3}], "mrfwashere": [{"id": 1115920, "mc": 496, "oc": 5}], "mrpapabaer": [{"id": 1116489, "mc": 101, "oc": 8}], "mrswitch33": [{"id": 1116571, "mc": 146, "oc": 26}], "mrdeco": [{"id": 1117230, "mc": 91, "oc": 6}], "mrkibblezworth": [{"id": 1117438, "mc": 1, "oc": 0}], "mrpsychoticyt": [{"id": 1117954, "mc": 117, "oc": 17}, {"id": 1140050, "mc": 103, "oc": 14}], "mrferruzca": [{"id": 1118111, "mc": 280, "oc": 80}, {"id": 1124894, "mc": 534, "oc": 102}], "mrblitz69": [{"id": 1118112, "mc": 48, "oc": 15}], "mrunsleepy": [{"id": 1118250, "mc": 11, "oc": 3}], "mrburrito": [{"id": 1118299, "mc": 127, "oc": 13}], "mrtiki": [{"id": 1118345, "mc": 1092, "oc": 107}], "mrrblitzz": [{"id": 1118471, "mc": 28, "oc": 3}], "mrdino": [{"id": 1118688, "mc": 7, "oc": 2}], "mrbavo94": [{"id": 1118750, "mc": 34, "oc": 9}], "mrjgrim": [{"id": 1118764, "mc": 47, "oc": 12}], "mrleftshark": [{"id": 1118856, "mc": 32, "oc": 8}], "mrdim452": [{"id": 1119060, "mc": 271, "oc": 37}], "mrlicornedu10": [{"id": 1119117, "mc": 19, "oc": 10}], "mrspootang": [{"id": 1119164, "mc": 22, "oc": 6}], "mrdragonfox": [{"id": 1119383, "mc": 186, "oc": 44}], "mrrabbertklein": [{"id": 1120069, "mc": 1, "oc": 0}], "mrz": [{"id": 1120231, "mc": 7, "oc": 1}, {"id": 1179370, "mc": 330, "oc": 15}], "mrartix": [{"id": 1120410, "mc": 289, "oc": 30}], "mrexpence": [{"id": 1120511, "mc": 10, "oc": 2}], "mrkanxz4k": [{"id": 1120521, "mc": 907, "oc": 75}], "mrsebm": [{"id": 1120760, "mc": 20, "oc": 3}], "mrzykot": [{"id": 1120835, "mc": 39, "oc": 7}], "mrpancaker": [{"id": 1121319, "mc": 33, "oc": 1}], "mrakavangardov": [{"id": 1121375, "mc": 39, "oc": 7}], "mrcerb": [{"id": 1121640, "mc": 405, "oc": 79}], "mrgredy": [{"id": 1121652, "mc": 64, "oc": 3}], "mrsthorhammered": [{"id": 1121697, "mc": 4, "oc": 0}], "mrwhite": [{"id": 1121708, "mc": 35, "oc": 6}], "mrasazelio": [{"id": 1122245, "mc": 88, "oc": 19}], "mryeetingson": [{"id": 1122400, "mc": 832, "oc": 72}], "mrz740": [{"id": 1123012, "mc": 9, "oc": 2}], "mrmarleytv": [{"id": 1123208, "mc": 59, "oc": 8}], "mrg4mepl4ce": [{"id": 1123379, "mc": 48, "oc": 7}], "mrshokoalat": [{"id": 1123413, "mc": 15, "oc": 9}], "mrsvb625532": [{"id": 1123493, "mc": 32, "oc": 8}], "mrrharper": [{"id": 1123505, "mc": 164, "oc": 10}], "mrauto69": [{"id": 1123803, "mc": 142, "oc": 41}], "mrmagicsheep": [{"id": 1123979, "mc": 463, "oc": 59}], "mrbob40": [{"id": 1124181, "mc": 14, "oc": 4}], "mrwhitetoaster": [{"id": 1124484, "mc": 1128, "oc": 92}], "mrkoffeetv": [{"id": 1124621, "mc": 318, "oc": 21}], "mrcarwen": [{"id": 1125021, "mc": 233, "oc": 12}], "mrmcgrittle": [{"id": 1125629, "mc": 21, "oc": 4}], "mreismentv": [{"id": 1125640, "mc": 219, "oc": 52}], "mrfelon": [{"id": 1125647, "mc": 9158, "oc": 817}], "mrspacemanguy": [{"id": 1125827, "mc": 66, "oc": 11}], "mrhawee": [{"id": 1126035, "mc": 368, "oc": 15}], "mrdollywhite": [{"id": 1126200, "mc": 58, "oc": 15}], "mrhorder": [{"id": 1126292, "mc": 37, "oc": 3}], "mrsabtv": [{"id": 1126444, "mc": 1435, "oc": 108}, {"id": 1203249, "mc": 503, "oc": 53}], "mrbazibaz": [{"id": 1127154, "mc": 68, "oc": 14}], "mrwomanstealer": [{"id": 1127194, "mc": 2, "oc": 2}], "mrpeper": [{"id": 1127318, "mc": 45, "oc": 14}], "mrboyd": [{"id": 1127495, "mc": 1, "oc": 1}], "mrtu619": [{"id": 1127720, "mc": 83, "oc": 24}], "mrnoir": [{"id": 1127723, "mc": 66, "oc": 31}], "mrelrikilmc": [{"id": 1127906, "mc": 111, "oc": 15}], "mrtoto77": [{"id": 1128080, "mc": 45, "oc": 4}], "mrsin420": [{"id": 1128137, "mc": 562, "oc": 52}], "mrtestone": [{"id": 1128232, "mc": 16, "oc": 0}], "mrzef": [{"id": 1128375, "mc": 83, "oc": 14}], "mrjomiz": [{"id": 1128551, "mc": 44, "oc": 2}], "mrdd616": [{"id": 1129063, "mc": 5, "oc": 1}], "mrjaytv": [{"id": 1129155, "mc": 40, "oc": 11}, {"id": 1192979, "mc": 405, "oc": 63}], "mrperfectrecord": [{"id": 1129189, "mc": 6208, "oc": 952}], "mrsheeplive": [{"id": 1129376, "mc": 554, "oc": 91}], "mrslampex": [{"id": 1129487, "mc": 98, "oc": 11}], "mrduckey693723": [{"id": 1129605, "mc": 41, "oc": 6}], "mrkk022": [{"id": 1130347, "mc": 2641, "oc": 145}], "mrbrutal777": [{"id": 1130468, "mc": 7, "oc": 1}], "mroozer": [{"id": 1130628, "mc": 49, "oc": 18}], "mrbeanpfc": [{"id": 1130657, "mc": 164, "oc": 27}], "mrdoctor540": [{"id": 1131577, "mc": 19, "oc": 5}], "mrcangrejo": [{"id": 1131736, "mc": 173, "oc": 18}], "mrhopstv": [{"id": 1131887, "mc": 212, "oc": 20}], "mrmarkhayward": [{"id": 1131996, "mc": 35, "oc": 15}], "mrssblossom": [{"id": 1132446, "mc": 24, "oc": 6}], "mrstubbinz": [{"id": 1132496, "mc": 59, "oc": 15}], "mrfotog": [{"id": 1132534, "mc": 147, "oc": 35}], "mrbrodinha": [{"id": 1132620, "mc": 70, "oc": 11}], "mrdiamonddog": [{"id": 1132825, "mc": 22, "oc": 1}], "mrmaui2": [{"id": 1133479, "mc": 7, "oc": 2}], "mr2platypu": [{"id": 1134503, "mc": 56, "oc": 11}], "mryacudza": [{"id": 1134709, "mc": 152, "oc": 16}], "mrcappy1": [{"id": 1134726, "mc": 85, "oc": 14}], "mrpr1993": [{"id": 1134983, "mc": 144, "oc": 26}], "mrpsikoz": [{"id": 1135168, "mc": 79, "oc": 9}], "mrshake": [{"id": 1135387, "mc": 77, "oc": 19}], "mrmatrixm51": [{"id": 1135452, "mc": 106, "oc": 25}], "mrmoabii": [{"id": 1135650, "mc": 67, "oc": 10}], "mrmentoler630": [{"id": 1135785, "mc": 61, "oc": 7}], "mrdokker": [{"id": 1136661, "mc": 10, "oc": 1}], "mrforgottable": [{"id": 1136700, "mc": 76, "oc": 5}], "mrmikedev": [{"id": 1136735, "mc": 14, "oc": 2}], "mrinin": [{"id": 1136747, "mc": 168, "oc": 21}], "mrbasketballm": [{"id": 1137113, "mc": 44, "oc": 7}], "mrfab7": [{"id": 1137377, "mc": 12, "oc": 6}], "mrmaddnes": [{"id": 1137538, "mc": 282, "oc": 16}], "mrlagg16": [{"id": 1137588, "mc": 17, "oc": 5}, {"id": 1143395, "mc": 40, "oc": 11}, {"id": 1245001, "mc": 8, "oc": 5}], "mrfear0714": [{"id": 1137743, "mc": 235, "oc": 35}, {"id": 1187671, "mc": 51, "oc": 20}], "mrplayeryork": [{"id": 1137783, "mc": 114, "oc": 32}], "mrkotya": [{"id": 1137810, "mc": 77, "oc": 10}], "mrsthing": [{"id": 1138000, "mc": 45, "oc": 10}], "mrredstonetogo": [{"id": 1138102, "mc": 11, "oc": 3}], "mrshanik": [{"id": 1138242, "mc": 71, "oc": 12}], "mrconkin": [{"id": 1138315, "mc": 316, "oc": 23}], "mrgoemon": [{"id": 1138319, "mc": 82, "oc": 9}], "mrloopsx": [{"id": 1138468, "mc": 480, "oc": 81}], "mririshire": [{"id": 1138492, "mc": 57, "oc": 23}], "mratagun": [{"id": 1138634, "mc": 24, "oc": 2}], "mrszeregowy": [{"id": 1138655, "mc": 175, "oc": 14}], "mrsyellowyana": [{"id": 1138818, "mc": 118, "oc": 34}], "mrgovard": [{"id": 1139080, "mc": 426, "oc": 30}], "mr1weasel": [{"id": 1139185, "mc": 41, "oc": 13}], "mrrosadottv": [{"id": 1139932, "mc": 16, "oc": 5}], "mrhampter": [{"id": 1139996, "mc": 39, "oc": 10}], "mrslaptastic": [{"id": 1140002, "mc": 12, "oc": 5}], "mrhappystore": [{"id": 1140241, "mc": 22, "oc": 3}], "mr8strike": [{"id": 1140533, "mc": 37, "oc": 14}], "mrunknown200x": [{"id": 1140651, "mc": 80, "oc": 40}], "mrdarvi": [{"id": 1140725, "mc": 75, "oc": 20}], "mrvxx": [{"id": 1141050, "mc": 66, "oc": 6}], "mrzgabor": [{"id": 1141092, "mc": 81, "oc": 13}], "mrsauro": [{"id": 1141327, "mc": 68, "oc": 10}], "mrivanovichh": [{"id": 1141638, "mc": 659, "oc": 100}, {"id": 1176284, "mc": 266, "oc": 55}, {"id": 1248395, "mc": 1726, "oc": 326}], "mrdankuraz": [{"id": 1141932, "mc": 918, "oc": 20}], "mrurlvibez": [{"id": 1141968, "mc": 22, "oc": 9}, {"id": 1238391, "mc": 71, "oc": 16}], "mrmellow": [{"id": 1141997, "mc": 21, "oc": 5}], "mrpathfinder": [{"id": 1142134, "mc": 104, "oc": 43}], "mrfreeman4707": [{"id": 1142657, "mc": 58, "oc": 8}], "mrsavage": [{"id": 1142685, "mc": 17730, "oc": 1479}], "mrvnchan": [{"id": 1142976, "mc": 140, "oc": 32}], "mrsaif2": [{"id": 1143330, "mc": 6, "oc": 3}], "mrbeowulf": [{"id": 1143841, "mc": 121, "oc": 25}], "mrvltn59": [{"id": 1144234, "mc": 35, "oc": 4}], "mri": [{"id": 1144424, "mc": 15864, "oc": 2152}], "mrharryw": [{"id": 1144576, "mc": 2838, "oc": 29}, {"id": 1181158, "mc": 117, "oc": 34}], "mrgintel": [{"id": 1144613, "mc": 45, "oc": 8}], "mratlanticboii": [{"id": 1144663, "mc": 1, "oc": 0}], "mrhal": [{"id": 1144737, "mc": 77, "oc": 15}], "mrpetsito": [{"id": 1144872, "mc": 49, "oc": 6}], "mrspock2230": [{"id": 1145096, "mc": 33, "oc": 3}], "mrps": [{"id": 1145476, "mc": 51, "oc": 10}], "mrandrew2007": [{"id": 1145571, "mc": 3965, "oc": 214}], "mrdead": [{"id": 1146277, "mc": 230, "oc": 29}], "mrnekotine": [{"id": 1146319, "mc": 197, "oc": 17}], "mredispop": [{"id": 1146405, "mc": 35, "oc": 7}], "mrkasenzangakhona": [{"id": 1147866, "mc": 42, "oc": 12}], "mrbinksgaming": [{"id": 1148320, "mc": 1, "oc": 0}], "mruncalled": [{"id": 1148339, "mc": 38, "oc": 0}], "mremee": [{"id": 1148390, "mc": 123, "oc": 36}], "mrender1859": [{"id": 1148794, "mc": 387, "oc": 95}], "mr01sam": [{"id": 1149165, "mc": 155, "oc": 36}], "mrflox888": [{"id": 1149921, "mc": 29, "oc": 6}], "mrgrand": [{"id": 1149946, "mc": 104, "oc": 14}], "mrsonicmanu": [{"id": 1149972, "mc": 18, "oc": 2}], "mrcraft777": [{"id": 1150721, "mc": 27, "oc": 4}, {"id": 1170007, "mc": 1, "oc": 1}, {"id": 1203333, "mc": 22, "oc": 6}, {"id": 1207632, "mc": 125, "oc": 28}, {"id": 1222308, "mc": 7, "oc": 2}], "mrmoneyttm": [{"id": 1150833, "mc": 35, "oc": 5}], "mrsekai": [{"id": 1150974, "mc": 1466, "oc": 171}, {"id": 1208485, "mc": 561, "oc": 123}], "mrsl4ck3r": [{"id": 1151111, "mc": 271, "oc": 36}], "mrearles": [{"id": 1151152, "mc": 28, "oc": 5}], "mrtoogreedy": [{"id": 1151892, "mc": 115, "oc": 2}], "mrandersen": [{"id": 1151905, "mc": 61, "oc": 11}], "mraladin": [{"id": 1152044, "mc": 220, "oc": 41}], "mrxquaples8783": [{"id": 1152572, "mc": 3, "oc": 0}], "mrj0ker733": [{"id": 1152708, "mc": 17, "oc": 7}], "mrstealyoyogurt": [{"id": 1152951, "mc": 55, "oc": 20}], "mrcarre": [{"id": 1152987, "mc": 36, "oc": 5}], "mrloc": [{"id": 1153237, "mc": 204, "oc": 2}], "mrbrokenpancrea": [{"id": 1153495, "mc": 33, "oc": 5}], "mrmeems27": [{"id": 1153557, "mc": 1, "oc": 1}], "mrpatita": [{"id": 1153569, "mc": 462, "oc": 38}], "mrvanylla": [{"id": 1154142, "mc": 17, "oc": 3}], "mrinvidioso": [{"id": 1154195, "mc": 4560, "oc": 624}], "mrfinnymore": [{"id": 1154568, "mc": 148, "oc": 21}], "mrpeggle": [{"id": 1155075, "mc": 169, "oc": 23}], "mrcryptic": [{"id": 1155130, "mc": 8, "oc": 1}], "mrmahoghany": [{"id": 1155178, "mc": 123, "oc": 38}], "mrfoo": [{"id": 1155233, "mc": 31, "oc": 6}], "mrpictel": [{"id": 1155448, "mc": 48, "oc": 13}], "mryolo": [{"id": 1155451, "mc": 67, "oc": 9}], "mrnanotiaccaci": [{"id": 1155876, "mc": 150, "oc": 13}], "mrphilipbone": [{"id": 1156640, "mc": 114, "oc": 17}], "mrpepsikk": [{"id": 1157019, "mc": 104, "oc": 18}], "mrgaming20": [{"id": 1157251, "mc": 503, "oc": 12}], "mrminecraft02": [{"id": 1157619, "mc": 42, "oc": 6}], "mrorange9jct": [{"id": 1157968, "mc": 4, "oc": 0}], "mrbakenbitz": [{"id": 1158007, "mc": 76, "oc": 5}], "mrpani93": [{"id": 1158089, "mc": 16, "oc": 0}], "mrrayithab": [{"id": 1158433, "mc": 135, "oc": 11}], "mrragepanda": [{"id": 1158491, "mc": 6, "oc": 0}], "mr0v0": [{"id": 1158625, "mc": 13, "oc": 10}], "mr1glitch": [{"id": 1158923, "mc": 13, "oc": 8}], "mrwoozle": [{"id": 1158924, "mc": 40, "oc": 9}], "mrepiccarrots8643": [{"id": 1159026, "mc": 1, "oc": 0}], "mrpanos1212": [{"id": 1159284, "mc": 179, "oc": 38}], "mrguada99": [{"id": 1159337, "mc": 80, "oc": 9}], "mrraichugf": [{"id": 1159903, "mc": 40, "oc": 1}], "mrtommygamz": [{"id": 1160543, "mc": 19, "oc": 8}], "mrtun121": [{"id": 1160854, "mc": 69, "oc": 3}], "mrflooky": [{"id": 1160914, "mc": 24, "oc": 7}], "mrmeowgi": [{"id": 1161280, "mc": 39, "oc": 6}], "mrburns010": [{"id": 1161402, "mc": 2702, "oc": 286}], "mrmary101": [{"id": 1161403, "mc": 27, "oc": 2}], "mrqwertyperty": [{"id": 1161507, "mc": 69, "oc": 26}], "mralfacat": [{"id": 1161511, "mc": 10, "oc": 0}], "mramos12": [{"id": 1161976, "mc": 32, "oc": 10}], "mrdeadbird": [{"id": 1162700, "mc": 13, "oc": 1}], "mrisoloman": [{"id": 1163057, "mc": 14, "oc": 8}], "mrwickpt": [{"id": 1163140, "mc": 87, "oc": 15}], "mrzeboy": [{"id": 1163371, "mc": 12, "oc": 8}], "mrgoof3": [{"id": 1163585, "mc": 1, "oc": 0}], "mrcarbongamingtv": [{"id": 1164219, "mc": 24, "oc": 7}], "mrzenco": [{"id": 1164297, "mc": 11, "oc": 3}], "mrkay": [{"id": 1164444, "mc": 44, "oc": 14}], "mrwicket": [{"id": 1164954, "mc": 90, "oc": 23}], "mrnahuel": [{"id": 1165027, "mc": 233, "oc": 21}], "mrmercurypower": [{"id": 1165821, "mc": 126, "oc": 9}], "mrgreenity420": [{"id": 1166350, "mc": 67, "oc": 16}], "mrtakdnz": [{"id": 1166401, "mc": 4, "oc": 2}], "mrprofyt7": [{"id": 1166602, "mc": 24, "oc": 9}], "mrcl0udman420": [{"id": 1167159, "mc": 52, "oc": 11}], "mrsobiejaro": [{"id": 1168028, "mc": 86, "oc": 18}], "mrpopzicle": [{"id": 1168280, "mc": 30, "oc": 8}], "mrsknive": [{"id": 1168440, "mc": 76, "oc": 9}], "mrcreeperfire": [{"id": 1168480, "mc": 67, "oc": 9}], "mrstriumviri": [{"id": 1168540, "mc": 150, "oc": 19}], "mrty": [{"id": 1168560, "mc": 283, "oc": 23}], "mrplumber69": [{"id": 1168979, "mc": 19, "oc": 6}], "mrtgaming": [{"id": 1169355, "mc": 267, "oc": 102}], "mrmoringstarttv": [{"id": 1169558, "mc": 41, "oc": 11}], "mrmeem": [{"id": 1170001, "mc": 2, "oc": 1}], "mrguitoune": [{"id": 1170121, "mc": 122, "oc": 21}], "mrthirdwheel": [{"id": 1170578, "mc": 56, "oc": 8}], "mrfrank0121": [{"id": 1170625, "mc": 9, "oc": 2}], "mrharshgamer": [{"id": 1170882, "mc": 4, "oc": 0}], "mrdavkill": [{"id": 1170957, "mc": 60, "oc": 13}], "mrmike087992": [{"id": 1171722, "mc": 19, "oc": 4}], "mrchefkev7": [{"id": 1172050, "mc": 109, "oc": 35}], "mrshotik": [{"id": 1172094, "mc": 25, "oc": 4}], "mr420uk": [{"id": 1172238, "mc": 17, "oc": 7}], "mrjohnyjr": [{"id": 1172371, "mc": 28, "oc": 5}], "mrjam5875": [{"id": 1172448, "mc": 817, "oc": 119}], "mrknrt": [{"id": 1173048, "mc": 132, "oc": 15}], "mrpitufi": [{"id": 1173258, "mc": 10, "oc": 1}], "mrdonnittyog": [{"id": 1173811, "mc": 160, "oc": 36}], "mrburritoslayer": [{"id": 1174162, "mc": 98, "oc": 10}], "mrbunny32": [{"id": 1174358, "mc": 45, "oc": 15}], "mrdungeonsan": [{"id": 1174611, "mc": 84, "oc": 17}], "mrjuliano": [{"id": 1174936, "mc": 31, "oc": 5}], "mrgakuto": [{"id": 1174950, "mc": 42, "oc": 5}], "mrlm": [{"id": 1175176, "mc": 104, "oc": 14}], "mroof2353": [{"id": 1175184, "mc": 15, "oc": 7}], "mrpinson": [{"id": 1175231, "mc": 37, "oc": 3}], "mrow0": [{"id": 1175385, "mc": 578, "oc": 113}], "mrwootastic": [{"id": 1175529, "mc": 168, "oc": 31}], "mrpheromone": [{"id": 1175955, "mc": 301, "oc": 21}], "mrafitol": [{"id": 1176013, "mc": 59, "oc": 19}], "mropinion": [{"id": 1176472, "mc": 63, "oc": 13}], "mrvignac": [{"id": 1176516, "mc": 66, "oc": 9}], "mrsgoldschakal": [{"id": 1176592, "mc": 53, "oc": 14}], "mrnoodle": [{"id": 1176608, "mc": 90, "oc": 21}], "mrsilkasmr": [{"id": 1176676, "mc": 349, "oc": 78}], "mrradicalbomb": [{"id": 1177065, "mc": 13, "oc": 1}], "mralleda": [{"id": 1177373, "mc": 219, "oc": 14}], "mrdelicioustaco": [{"id": 1177574, "mc": 52, "oc": 9}], "mrbraveshot": [{"id": 1177679, "mc": 247, "oc": 32}], "mrpres": [{"id": 1178095, "mc": 163, "oc": 33}], "mrnoobnub": [{"id": 1178571, "mc": 119, "oc": 31}], "mrbeard93": [{"id": 1178579, "mc": 34, "oc": 8}], "mrshiba": [{"id": 1178955, "mc": 23, "oc": 3}], "mrbakakoda": [{"id": 1179168, "mc": 101, "oc": 21}], "mrhyper5856": [{"id": 1179249, "mc": 28, "oc": 15}], "mrdanslite": [{"id": 1179254, "mc": 15, "oc": 5}], "mrdeathus": [{"id": 1179490, "mc": 120, "oc": 9}], "mrodom": [{"id": 1179976, "mc": 74, "oc": 22}], "mrjorjaisxd": [{"id": 1180038, "mc": 14, "oc": 5}], "mreclipse": [{"id": 1180233, "mc": 12, "oc": 6}], "mrscary66": [{"id": 1180342, "mc": 338, "oc": 62}], "mredvinbro": [{"id": 1180377, "mc": 270, "oc": 5}], "mrbear": [{"id": 1180396, "mc": 7140, "oc": 512}], "mrdino606": [{"id": 1181027, "mc": 67, "oc": 9}], "mroilman": [{"id": 1181280, "mc": 48, "oc": 20}], "mrsyonk": [{"id": 1181457, "mc": 26, "oc": 8}], "mrpinitagg": [{"id": 1181549, "mc": 80, "oc": 5}], "mrsolo66": [{"id": 1181697, "mc": 47, "oc": 6}], "mrastrophysicist": [{"id": 1182003, "mc": 57, "oc": 19}], "mrchilled85": [{"id": 1182191, "mc": 153, "oc": 25}], "mrunknownde": [{"id": 1182528, "mc": 52, "oc": 11}], "mrmmuscle": [{"id": 1182969, "mc": 85, "oc": 22}], "mrjuliu": [{"id": 1183217, "mc": 75, "oc": 25}], "mrcharmander0855": [{"id": 1183471, "mc": 212, "oc": 12}], "mrrookiie": [{"id": 1184104, "mc": 112, "oc": 21}], "mrbastounet": [{"id": 1184187, "mc": 196, "oc": 32}], "mrcarbohydrate": [{"id": 1184786, "mc": 248, "oc": 77}], "mrbladettv": [{"id": 1184974, "mc": 10, "oc": 0}], "mrxerto": [{"id": 1185538, "mc": 8, "oc": 2}], "mrstarkov01": [{"id": 1185563, "mc": 9, "oc": 1}], "mragent": [{"id": 1185610, "mc": 109, "oc": 21}], "mrv0rnexx": [{"id": 1185703, "mc": 9, "oc": 5}], "mrspoem": [{"id": 1185869, "mc": 153, "oc": 31}], "mrpastelitoo": [{"id": 1186373, "mc": 747, "oc": 31}], "mredit11": [{"id": 1186563, "mc": 46, "oc": 6}], "mrphxaz": [{"id": 1186609, "mc": 83, "oc": 19}], "mrbill98": [{"id": 1187195, "mc": 21, "oc": 5}, {"id": 1236546, "mc": 169, "oc": 42}], "mrsh4d0w": [{"id": 1187358, "mc": 16, "oc": 4}], "mrtreecat": [{"id": 1187600, "mc": 22, "oc": 7}], "mrfish2007": [{"id": 1187656, "mc": 5, "oc": 0}], "mrocco525": [{"id": 1187758, "mc": 15, "oc": 4}], "mrcloista": [{"id": 1187894, "mc": 166, "oc": 49}], "mrlincolnx": [{"id": 1188351, "mc": 88, "oc": 41}], "mrtommo2304": [{"id": 1188423, "mc": 2236, "oc": 228}], "mrbooks1123": [{"id": 1188607, "mc": 60, "oc": 1}], "mrshawn12": [{"id": 1188973, "mc": 479, "oc": 34}], "mreh": [{"id": 1189067, "mc": 773, "oc": 32}], "mrkymz": [{"id": 1189227, "mc": 343, "oc": 27}], "mraknomark": [{"id": 1189586, "mc": 36, "oc": 15}], "mrseismic": [{"id": 1189786, "mc": 90, "oc": 29}], "mrandersonxxviii": [{"id": 1189917, "mc": 74, "oc": 12}], "mrbloot0467": [{"id": 1189924, "mc": 25, "oc": 1}], "mrahs2": [{"id": 1190430, "mc": 74, "oc": 13}], "mrbanhmi": [{"id": 1190452, "mc": 88, "oc": 31}], "mrskrank": [{"id": 1191394, "mc": 175, "oc": 31}], "mrtomatito": [{"id": 1192745, "mc": 249, "oc": 15}], "mrsroni": [{"id": 1193367, "mc": 447, "oc": 56}], "mrgood": [{"id": 1193503, "mc": 6, "oc": 0}], "mryeeee": [{"id": 1193687, "mc": 714, "oc": 283}], "mrsantiagosr": [{"id": 1193715, "mc": 35, "oc": 6}], "mrreeeee": [{"id": 1194318, "mc": 425, "oc": 159}], "mraxetv": [{"id": 1194347, "mc": 32, "oc": 6}], "mrdiesel85": [{"id": 1194377, "mc": 153, "oc": 35}], "mrpodder": [{"id": 1194591, "mc": 32, "oc": 7}], "mrpoisonx": [{"id": 1194998, "mc": 35, "oc": 7}], "mrchip": [{"id": 1195207, "mc": 272, "oc": 41}], "mrcorleone": [{"id": 1195278, "mc": 402, "oc": 53}], "mrtimmy41": [{"id": 1195328, "mc": 238, "oc": 36}], "mrqqq": [{"id": 1195340, "mc": 70, "oc": 22}], "mrsatvik": [{"id": 1195363, "mc": 152, "oc": 30}], "mrlegend9": [{"id": 1195403, "mc": 128, "oc": 23}], "mranttenn4": [{"id": 1196202, "mc": 234, "oc": 43}], "mrbang": [{"id": 1196338, "mc": 113, "oc": 17}], "mrzoggha": [{"id": 1196735, "mc": 112, "oc": 16}], "mrdrasticexe5646": [{"id": 1196946, "mc": 21, "oc": 10}], "mrdjflyhi": [{"id": 1197190, "mc": 28, "oc": 6}], "mrweeknie": [{"id": 1197562, "mc": 91, "oc": 24}], "mrspaghetti": [{"id": 1197642, "mc": 6429, "oc": 784}], "mrzippertit": [{"id": 1198072, "mc": 21, "oc": 7}], "mrpuffa": [{"id": 1198283, "mc": 89, "oc": 10}], "mrmoko": [{"id": 1198312, "mc": 16, "oc": 2}], "mrtophatdev": [{"id": 1198606, "mc": 2, "oc": 1}], "mrblaetsch": [{"id": 1198762, "mc": 102, "oc": 12}], "mrsirpatche": [{"id": 1198784, "mc": 51, "oc": 9}], "mrmiesta": [{"id": 1199370, "mc": 91, "oc": 25}], "mrkap": [{"id": 1199495, "mc": 90, "oc": 17}], "mrgenocider": [{"id": 1199732, "mc": 34, "oc": 9}], "mrn6941": [{"id": 1199780, "mc": 716, "oc": 105}], "mr3bkreno": [{"id": 1199895, "mc": 568, "oc": 79}], "mrtino": [{"id": 1200133, "mc": 65, "oc": 18}], "mrtoroloko": [{"id": 1200200, "mc": 75, "oc": 14}], "mrkrunklord": [{"id": 1200301, "mc": 84, "oc": 17}], "mrhorse2442": [{"id": 1200500, "mc": 45, "oc": 8}], "mrevaasion": [{"id": 1200507, "mc": 18, "oc": 6}], "mrmnichubright": [{"id": 1201031, "mc": 23, "oc": 8}], "mrmilo": [{"id": 1201265, "mc": 12, "oc": 6}], "mrhaskijz": [{"id": 1201329, "mc": 151, "oc": 35}], "mrfatfinger": [{"id": 1201471, "mc": 31, "oc": 8}], "mrgaliant": [{"id": 1202755, "mc": 56, "oc": 8}], "mrwharry": [{"id": 1202876, "mc": 27, "oc": 6}], "mrs4rdo": [{"id": 1202951, "mc": 53, "oc": 11}], "mrksyun": [{"id": 1203542, "mc": 49, "oc": 14}], "mrecel": [{"id": 1203776, "mc": 66, "oc": 6}], "mrwilltv": [{"id": 1204176, "mc": 956, "oc": 71}], "mrfuzzx": [{"id": 1204601, "mc": 82, "oc": 15}], "mrlaki": [{"id": 1204750, "mc": 3, "oc": 0}], "mrn04804": [{"id": 1204961, "mc": 48, "oc": 5}], "mrscreamy": [{"id": 1205226, "mc": 74, "oc": 19}], "mregmor": [{"id": 1205286, "mc": 3072, "oc": 338}], "mrclownbr": [{"id": 1205507, "mc": 4, "oc": 0}], "mrbeastzyuczek135": [{"id": 1205712, "mc": 79, "oc": 26}], "mremo": [{"id": 1206238, "mc": 10, "oc": 3}], "mrx7008": [{"id": 1206290, "mc": 6, "oc": 4}], "mrinkryption": [{"id": 1206815, "mc": 12, "oc": 1}], "mrbrokenhand": [{"id": 1207252, "mc": 209, "oc": 19}], "mravilet": [{"id": 1207775, "mc": 51, "oc": 7}], "mrmaniadc": [{"id": 1207892, "mc": 183, "oc": 41}], "mrnlgamingyt": [{"id": 1208197, "mc": 61, "oc": 14}], "mrbeardstone": [{"id": 1208338, "mc": 5156, "oc": 1338}], "mrpancake4343": [{"id": 1208915, "mc": 10371, "oc": 1058}], "mrhousemdawesomenes": [{"id": 1209082, "mc": 14, "oc": 4}], "mrquinti": [{"id": 1209576, "mc": 51, "oc": 16}], "mrcryptodk": [{"id": 1209636, "mc": 205, "oc": 12}], "mrbutler32": [{"id": 1209895, "mc": 68, "oc": 17}], "mrcowdisease1": [{"id": 1210535, "mc": 9, "oc": 2}], "mrbob5570": [{"id": 1210979, "mc": 11, "oc": 4}], "mrnordaleburda": [{"id": 1211276, "mc": 29, "oc": 9}], "mrnoskillz": [{"id": 1211310, "mc": 43, "oc": 8}], "mrkiwi": [{"id": 1211730, "mc": 227, "oc": 54}], "mriilk": [{"id": 1211954, "mc": 27, "oc": 13}], "mrran8989": [{"id": 1212451, "mc": 272, "oc": 12}], "mrcharlesjr": [{"id": 1212553, "mc": 30, "oc": 13}], "mrcheezedoodle22": [{"id": 1213717, "mc": 54, "oc": 8}], "mrtourte": [{"id": 1213885, "mc": 106, "oc": 21}], "mrchickengg": [{"id": 1214001, "mc": 103, "oc": 18}], "mralve": [{"id": 1214262, "mc": 204, "oc": 48}, {"id": 1223505, "mc": 884, "oc": 142}], "mrfrip": [{"id": 1214421, "mc": 171, "oc": 30}], "mrcompotion": [{"id": 1214531, "mc": 90, "oc": 14}], "mrs66sick": [{"id": 1214735, "mc": 56, "oc": 15}], "mrissayt": [{"id": 1214910, "mc": 44, "oc": 12}], "mrmrmystery": [{"id": 1215039, "mc": 42, "oc": 6}], "mrbepic": [{"id": 1215665, "mc": 68, "oc": 14}], "mrtham": [{"id": 1216336, "mc": 319, "oc": 59}], "mrsphilpickle": [{"id": 1216358, "mc": 118, "oc": 27}], "mrbeastlyshadow": [{"id": 1216619, "mc": 107, "oc": 17}], "mrtaylortoolarge": [{"id": 1216728, "mc": 93, "oc": 18}], "mrtom1308": [{"id": 1217236, "mc": 26, "oc": 4}], "mrpodzi": [{"id": 1218104, "mc": 30, "oc": 9}], "mrdpvkyu": [{"id": 1218229, "mc": 77, "oc": 5}], "mrbeastmmr": [{"id": 1218244, "mc": 99, "oc": 11}], "mrfeiler": [{"id": 1218333, "mc": 112, "oc": 21}], "mrminesheep": [{"id": 1218507, "mc": 2, "oc": 1}], "mrsnathaliej": [{"id": 1218713, "mc": 1, "oc": 0}], "mrlovely": [{"id": 1219203, "mc": 43, "oc": 8}], "mrjayford": [{"id": 1219436, "mc": 8, "oc": 0}], "mrhappyface": [{"id": 1219621, "mc": 473, "oc": 69}], "mrgn5710": [{"id": 1219735, "mc": 9, "oc": 1}], "mrdotkg": [{"id": 1220160, "mc": 2, "oc": 0}], "mrsbeav3698790": [{"id": 1220191, "mc": 2, "oc": 0}], "mrdickey": [{"id": 1220286, "mc": 51, "oc": 10}], "mrtotommy": [{"id": 1220305, "mc": 76, "oc": 15}], "mrscodelyokop": [{"id": 1220515, "mc": 37, "oc": 9}], "mrgolden32467": [{"id": 1220742, "mc": 2, "oc": 1}], "mr4damage": [{"id": 1220890, "mc": 118, "oc": 23}], "mrooriginal": [{"id": 1220989, "mc": 49, "oc": 9}], "mrick": [{"id": 1221236, "mc": 69, "oc": 29}], "mrknightsgaming": [{"id": 1221251, "mc": 65, "oc": 13}], "mrchiev": [{"id": 1221336, "mc": 24, "oc": 8}], "mrkristopher": [{"id": 1221404, "mc": 56, "oc": 6}], "mrhelix": [{"id": 1221479, "mc": 17, "oc": 8}], "mrgamenlift": [{"id": 1221798, "mc": 4, "oc": 0}], "mrspavn": [{"id": 1222326, "mc": 854, "oc": 58}], "mrraashi": [{"id": 1223451, "mc": 77, "oc": 22}], "mrlipx": [{"id": 1223752, "mc": 229, "oc": 22}], "mrmobetta13": [{"id": 1223812, "mc": 13, "oc": 1}], "mrshowpopper": [{"id": 1224343, "mc": 20, "oc": 4}], "mrpotter0058": [{"id": 1224488, "mc": 137, "oc": 7}], "mrpollollo": [{"id": 1225699, "mc": 82, "oc": 9}], "mrgrimreaper66": [{"id": 1225790, "mc": 14, "oc": 7}], "mrtwster": [{"id": 1225951, "mc": 2371, "oc": 225}], "mrsurveillance": [{"id": 1226131, "mc": 44, "oc": 9}], "mrorie": [{"id": 1226167, "mc": 9, "oc": 0}], "mrzoke": [{"id": 1226315, "mc": 138, "oc": 38}], "mrazb56": [{"id": 1226541, "mc": 21, "oc": 4}], "mrpresto": [{"id": 1226572, "mc": 384, "oc": 107}], "mrrazamataz": [{"id": 1226628, "mc": 12, "oc": 3}], "mrdensalt": [{"id": 1226969, "mc": 8991, "oc": 1324}], "mrfoloundev": [{"id": 1226973, "mc": 12, "oc": 4}], "mrjetit": [{"id": 1227282, "mc": 51, "oc": 12}], "mrdoc779": [{"id": 1227334, "mc": 241, "oc": 15}], "mrbottingnerd": [{"id": 1227355, "mc": 207, "oc": 62}], "mrarch777": [{"id": 1228164, "mc": 21, "oc": 12}], "mrglaze": [{"id": 1228557, "mc": 48, "oc": 7}], "mrpieczek": [{"id": 1228889, "mc": 19, "oc": 4}], "mrtomrod": [{"id": 1229773, "mc": 7, "oc": 0}], "mrazak": [{"id": 1230406, "mc": 205, "oc": 43}], "mrjair": [{"id": 1230457, "mc": 230, "oc": 17}], "mrsolitariovt": [{"id": 1231072, "mc": 84, "oc": 12}], "mr2swap": [{"id": 1231226, "mc": 389, "oc": 11}], "mrkimchi": [{"id": 1231243, "mc": 29, "oc": 10}], "mrsbadgal": [{"id": 1231408, "mc": 106, "oc": 14}], "mrfrenchmanager": [{"id": 1231476, "mc": 74, "oc": 7}], "mrplaguedocter": [{"id": 1232107, "mc": 9, "oc": 4}], "mrchiku007": [{"id": 1232265, "mc": 3661, "oc": 37}], "mrjmovieclub": [{"id": 1232272, "mc": 89, "oc": 3}], "mrdmp": [{"id": 1232328, "mc": 20, "oc": 3}], "mrdombie": [{"id": 1232380, "mc": 9, "oc": 4}], "mrsjellyburger": [{"id": 1232467, "mc": 205, "oc": 21}], "mrthildee": [{"id": 1232603, "mc": 251, "oc": 24}], "mrbonesteryt": [{"id": 1233122, "mc": 238, "oc": 32}], "mrquicko": [{"id": 1233610, "mc": 57, "oc": 16}], "mrg1ub": [{"id": 1233818, "mc": 30, "oc": 8}], "mrsdaddio": [{"id": 1234397, "mc": 37, "oc": 11}], "mrlorenc": [{"id": 1234401, "mc": 252, "oc": 23}], "mrtaz17": [{"id": 1234537, "mc": 17, "oc": 4}], "mrmefiuu": [{"id": 1234660, "mc": 17674, "oc": 3542}], "mrogalski": [{"id": 1234903, "mc": 3, "oc": 0}], "mrhydejive": [{"id": 1235201, "mc": 38, "oc": 11}], "mrderpthebirb": [{"id": 1235839, "mc": 8, "oc": 4}], "mric3man": [{"id": 1235956, "mc": 24, "oc": 2}], "mrspaml": [{"id": 1236321, "mc": 478, "oc": 53}], "mrgravlr": [{"id": 1236575, "mc": 61, "oc": 19}], "mrfreshpaki": [{"id": 1236619, "mc": 415, "oc": 27}], "mrbabadook91": [{"id": 1237645, "mc": 45, "oc": 17}], "mrdokilover1": [{"id": 1238092, "mc": 2, "oc": 0}], "mrjenska": [{"id": 1238557, "mc": 28, "oc": 6}], "mrbananaboii": [{"id": 1238985, "mc": 38, "oc": 9}], "mrfresh0": [{"id": 1240102, "mc": 569, "oc": 29}], "mrbeast4851": [{"id": 1240139, "mc": 93, "oc": 31}], "mrbeann96ttv": [{"id": 1240251, "mc": 116, "oc": 28}], "mrrubi": [{"id": 1240468, "mc": 6, "oc": 3}], "mraz4450": [{"id": 1240834, "mc": 82, "oc": 8}], "mrpuccilucci": [{"id": 1240920, "mc": 278, "oc": 70}], "mrrobotreborn": [{"id": 1241731, "mc": 104, "oc": 28}], "mrpl": [{"id": 1242590, "mc": 25, "oc": 7}], "mrfalconclaw": [{"id": 1242786, "mc": 9, "oc": 4}], "mrm1rror": [{"id": 1243116, "mc": 583, "oc": 50}], "mrcallumx": [{"id": 1243121, "mc": 52, "oc": 17}], "mrdimigo": [{"id": 1243670, "mc": 242, "oc": 61}], "mrr": [{"id": 1243917, "mc": 689, "oc": 58}], "mrstrikerkillz": [{"id": 1244084, "mc": 36, "oc": 20}], "mrzeller": [{"id": 1244115, "mc": 190, "oc": 43}], "mraz45": [{"id": 1244116, "mc": 87, "oc": 30}], "mrtex2002": [{"id": 1244838, "mc": 32, "oc": 12}], "mrsuperdom": [{"id": 1245106, "mc": 64, "oc": 18}], "mrdizon": [{"id": 1245392, "mc": 66, "oc": 21}], "mrrunnybum": [{"id": 1245435, "mc": 50, "oc": 11}], "mrsephy": [{"id": 1246041, "mc": 236, "oc": 46}], "mrcoderpro": [{"id": 1246366, "mc": 6, "oc": 2}], "mrvirus99": [{"id": 1246713, "mc": 96, "oc": 13}], "mralex175": [{"id": 1247265, "mc": 52, "oc": 8}], "mrsmiiiley": [{"id": 1247765, "mc": 33, "oc": 9}], "mrfob": [{"id": 1247774, "mc": 65, "oc": 9}], "mrkryptonitexx": [{"id": 1247867, "mc": 16, "oc": 4}], "mrwanx": [{"id": 1247980, "mc": 1650, "oc": 61}], "mrmanison": [{"id": 1248059, "mc": 26, "oc": 6}], "mrpiglr": [{"id": 1248653, "mc": 143, "oc": 27}], "mrholy": [{"id": 1249051, "mc": 96, "oc": 18}], "mryellowpl": [{"id": 1249234, "mc": 231, "oc": 57}]}