{"cker": [{"id": 1006571, "mc": 11, "oc": 4}, {"id": 1080270, "mc": 557, "oc": 77}, {"id": 1154373, "mc": 50, "oc": 11}], "cki": [{"id": 1010805, "mc": 167, "oc": 7}], "ckb": [{"id": 1015370, "mc": 7, "oc": 4}], "ck3": [{"id": 1017814, "mc": 203, "oc": 45}, {"id": 1046763, "mc": 128, "oc": 33}, {"id": 1075864, "mc": 737, "oc": 147}, {"id": 1241056, "mc": 151, "oc": 13}], "ck": [{"id": 1026239, "mc": 12, "oc": 3}, {"id": 1037948, "mc": 14, "oc": 1}, {"id": 1054433, "mc": 133, "oc": 3}, {"id": 1063405, "mc": 228, "oc": 56}, {"id": 1083620, "mc": 19, "oc": 2}, {"id": 1084322, "mc": 12, "oc": 4}, {"id": 1105518, "mc": 7, "oc": 0}, {"id": 1107638, "mc": 134, "oc": 21}, {"id": 1112651, "mc": 1, "oc": 0}, {"id": 1116263, "mc": 450, "oc": 9}, {"id": 1124325, "mc": 62, "oc": 2}, {"id": 1148193, "mc": 35, "oc": 16}, {"id": 1181552, "mc": 101, "oc": 26}, {"id": 1234903, "mc": 3, "oc": 0}], "ckol": [{"id": 1026843, "mc": 10357, "oc": 176}], "ck2": [{"id": 1033046, "mc": 414, "oc": 78}], "ckj": [{"id": 1042408, "mc": 30, "oc": 5}], "ckw": [{"id": 1044133, "mc": 141, "oc": 41}], "ckcasola": [{"id": 1047176, "mc": 14, "oc": 6}], "cking": [{"id": 1049488, "mc": 1, "oc": 0}, {"id": 1221446, "mc": 45, "oc": 4}], "ckn": [{"id": 1063619, "mc": 189, "oc": 19}], "ckmoore": [{"id": 1081529, "mc": 19, "oc": 3}], "cktron": [{"id": 1114398, "mc": 15, "oc": 7}], "cks": [{"id": 1122902, "mc": 15, "oc": 6}], "ckgaming": [{"id": 1140148, "mc": 2228, "oc": 176}], "ckcreator": [{"id": 1145945, "mc": 189, "oc": 14}], "ck2multyfr": [{"id": 1151402, "mc": 8, "oc": 1}], "ck7": [{"id": 1155549, "mc": 16072, "oc": 312}], "ckilgour": [{"id": 1163981, "mc": 226, "oc": 28}], "ckrecords2": [{"id": 1172859, "mc": 8, "oc": 0}], "ckariok": [{"id": 1211428, "mc": 41, "oc": 8}], "ckvl": [{"id": 1216247, "mc": 56, "oc": 6}], "ckiii": [{"id": 1236764, "mc": 62, "oc": 8}]}