{"00": [{"id": 1000281, "mc": 32, "oc": 9}, {"id": 1053013, "mc": 19, "oc": 7}, {"id": 1077208, "mc": 73, "oc": 6}, {"id": 1098005, "mc": 17, "oc": 8}, {"id": 1141091, "mc": 122, "oc": 16}, {"id": 1175157, "mc": 139, "oc": 22}, {"id": 1186303, "mc": 19, "oc": 7}, {"id": 1186303, "mc": 19, "oc": 7}, {"id": 1248909, "mc": 45, "oc": 16}], "0001": [{"id": 1000907, "mc": 141, "oc": 15}, {"id": 1061638, "mc": 33, "oc": 5}, {"id": 1064073, "mc": 5, "oc": 2}], "00mfy": [{"id": 1006243, "mc": 15, "oc": 6}], "002": [{"id": 1020666, "mc": 69, "oc": 11}, {"id": 1043945, "mc": 22, "oc": 4}, {"id": 1053740, "mc": 102, "oc": 8}], "0007": [{"id": 1025367, "mc": 665, "oc": 28}, {"id": 1204103, "mc": 4, "oc": 1}], "007": [{"id": 1027611, "mc": 3723, "oc": 0}, {"id": 1094831, "mc": 608, "oc": 38}, {"id": 1099374, "mc": 24, "oc": 12}, {"id": 1117288, "mc": 27, "oc": 1}, {"id": 1201109, "mc": 7, "oc": 3}, {"id": 1219414, "mc": 3, "oc": 0}], "0084": [{"id": 1036216, "mc": 5, "oc": 0}], "002x": [{"id": 1037032, "mc": 188, "oc": 5}], "009": [{"id": 1042348, "mc": 171, "oc": 38}], "000001": [{"id": 1047934, "mc": 64, "oc": 13}], "0012": [{"id": 1052795, "mc": 946, "oc": 82}], "0055": [{"id": 1061174, "mc": 49, "oc": 11}], "008b": [{"id": 1062034, "mc": 17, "oc": 7}], "00thundy": [{"id": 1062068, "mc": 564, "oc": 96}], "001": [{"id": 1073234, "mc": 4, "oc": 2}, {"id": 1082257, "mc": 32, "oc": 5}, {"id": 1122733, "mc": 10, "oc": 3}, {"id": 1162504, "mc": 52, "oc": 8}, {"id": 1188788, "mc": 32, "oc": 2}, {"id": 1213472, "mc": 26, "oc": 11}], "000000009live": [{"id": 1084604, "mc": 11, "oc": 2}], "0082": [{"id": 1091193, "mc": 31, "oc": 2}], "0000900001": [{"id": 1103996, "mc": 124, "oc": 25}], "0000": [{"id": 1106216, "mc": 1473, "oc": 49}, {"id": 1205949, "mc": 32, "oc": 2}, {"id": 1222635, "mc": 21, "oc": 5}, {"id": 1223148, "mc": 60, "oc": 12}], "00cash": [{"id": 1108892, "mc": 424, "oc": 24}], "0053": [{"id": 1121631, "mc": 306, "oc": 65}], "0041": [{"id": 1126607, "mc": 19, "oc": 3}], "00pm": [{"id": 1129926, "mc": 638, "oc": 38}], "00braincell": [{"id": 1136876, "mc": 28, "oc": 13}], "007chimney": [{"id": 1139933, "mc": 77, "oc": 12}], "00tez": [{"id": 1153118, "mc": 506, "oc": 56}], "0000000": [{"id": 1153862, "mc": 449, "oc": 80}], "00smurf": [{"id": 1154819, "mc": 560, "oc": 96}], "009123": [{"id": 1155866, "mc": 88, "oc": 0}], "0054": [{"id": 1170354, "mc": 29, "oc": 13}], "007serialgamer": [{"id": 1179367, "mc": 97, "oc": 12}], "007n7": [{"id": 1185988, "mc": 23, "oc": 13}, {"id": 1249372, "mc": 42, "oc": 10}], "0014": [{"id": 1198454, "mc": 16, "oc": 3}], "004": [{"id": 1199469, "mc": 132, "oc": 7}], "007staytrue": [{"id": 1220869, "mc": 32, "oc": 1}], "000": [{"id": 1229667, "mc": 74, "oc": 13}], "00electro": [{"id": 1249653, "mc": 2043, "oc": 725}]}