{"cyber": [{"id": 1005788, "mc": 2713, "oc": 197}, {"id": 1010619, "mc": 65, "oc": 5}, {"id": 1011432, "mc": 1349, "oc": 162}, {"id": 1021872, "mc": 1447, "oc": 258}, {"id": 1022482, "mc": 1463, "oc": 134}, {"id": 1022482, "mc": 1463, "oc": 134}, {"id": 1032805, "mc": 119, "oc": 23}, {"id": 1034042, "mc": 20, "oc": 14}, {"id": 1041215, "mc": 50, "oc": 5}, {"id": 1046353, "mc": 444, "oc": 40}, {"id": 1046523, "mc": 5027, "oc": 868}, {"id": 1058744, "mc": 90, "oc": 36}, {"id": 1060061, "mc": 420, "oc": 30}, {"id": 1070939, "mc": 1025, "oc": 24}, {"id": 1083039, "mc": 2655, "oc": 162}, {"id": 1101868, "mc": 118, "oc": 6}, {"id": 1105678, "mc": 315, "oc": 40}, {"id": 1110646, "mc": 17, "oc": 6}, {"id": 1113528, "mc": 474, "oc": 18}, {"id": 1116918, "mc": 233, "oc": 16}, {"id": 1125605, "mc": 28, "oc": 8}, {"id": 1127299, "mc": 21, "oc": 7}, {"id": 1129343, "mc": 76, "oc": 7}, {"id": 1145416, "mc": 258, "oc": 32}, {"id": 1151774, "mc": 207, "oc": 46}, {"id": 1175670, "mc": 63, "oc": 8}, {"id": 1191772, "mc": 235, "oc": 68}, {"id": 1194948, "mc": 259, "oc": 46}, {"id": 1218280, "mc": 28, "oc": 9}, {"id": 1218762, "mc": 561, "oc": 26}, {"id": 1230194, "mc": 325, "oc": 24}, {"id": 1231485, "mc": 104, "oc": 24}, {"id": 1239128, "mc": 82, "oc": 24}, {"id": 1239874, "mc": 84, "oc": 2}, {"id": 1242266, "mc": 1021, "oc": 210}], "cymraeg": [{"id": 1006731, "mc": 104, "oc": 8}], "cybersecurity": [{"id": 1009737, "mc": 1279, "oc": 143}, {"id": 1031713, "mc": 23196, "oc": 2641}, {"id": 1046523, "mc": 5027, "oc": 868}, {"id": 1053337, "mc": 666, "oc": 51}, {"id": 1058901, "mc": 458, "oc": 79}, {"id": 1060061, "mc": 420, "oc": 30}, {"id": 1062575, "mc": 671, "oc": 93}, {"id": 1062575, "mc": 671, "oc": 93}, {"id": 1062575, "mc": 671, "oc": 93}, {"id": 1063597, "mc": 1169, "oc": 9}, {"id": 1067520, "mc": 2521, "oc": 531}, {"id": 1077187, "mc": 4434, "oc": 304}, {"id": 1083661, "mc": 421, "oc": 74}, {"id": 1106752, "mc": 326, "oc": 24}, {"id": 1106752, "mc": 326, "oc": 24}, {"id": 1118905, "mc": 79, "oc": 7}, {"id": 1141572, "mc": 478, "oc": 40}, {"id": 1141572, "mc": 478, "oc": 40}, {"id": 1148882, "mc": 139, "oc": 6}, {"id": 1153110, "mc": 110, "oc": 13}, {"id": 1169481, "mc": 504, "oc": 54}, {"id": 1194801, "mc": 32, "oc": 9}, {"id": 1196122, "mc": 594, "oc": 37}, {"id": 1200318, "mc": 1443, "oc": 412}, {"id": 1214645, "mc": 3993, "oc": 154}, {"id": 1217354, "mc": 74, "oc": 8}, {"id": 1220920, "mc": 1731, "oc": 198}, {"id": 1221743, "mc": 15, "oc": 6}, {"id": 1226048, "mc": 252, "oc": 27}, {"id": 1229245, "mc": 19, "oc": 1}, {"id": 1235628, "mc": 1447, "oc": 91}, {"id": 1240574, "mc": 155, "oc": 38}, {"id": 1240574, "mc": 155, "oc": 38}, {"id": 1242657, "mc": 1232, "oc": 237}, {"id": 1248047, "mc": 161, "oc": 8}, {"id": 1248047, "mc": 161, "oc": 8}, {"id": 1249502, "mc": 40, "oc": 7}, {"id": 1249573, "mc": 462, "oc": 33}], "cyantube": [{"id": 1010574, "mc": 97, "oc": 12}], "cysipy": [{"id": 1011876, "mc": 404, "oc": 115}], "cyanvoxel": [{"id": 1012739, "mc": 2029, "oc": 704}], "cyberpunk": [{"id": 1013948, "mc": 5158, "oc": 134}, {"id": 1056261, "mc": 1747, "oc": 677}, {"id": 1078358, "mc": 95, "oc": 29}, {"id": 1081623, "mc": 617, "oc": 169}, {"id": 1094369, "mc": 479, "oc": 80}, {"id": 1097312, "mc": 42, "oc": 12}, {"id": 1115562, "mc": 702, "oc": 220}, {"id": 1128345, "mc": 208, "oc": 34}, {"id": 1165226, "mc": 257, "oc": 29}, {"id": 1179753, "mc": 1415, "oc": 290}, {"id": 1183280, "mc": 4, "oc": 0}, {"id": 1191969, "mc": 5, "oc": 1}, {"id": 1191969, "mc": 5, "oc": 1}, {"id": 1193344, "mc": 4857, "oc": 979}, {"id": 1196396, "mc": 23, "oc": 6}, {"id": 1206733, "mc": 47, "oc": 8}, {"id": 1208587, "mc": 992, "oc": 213}, {"id": 1210017, "mc": 57, "oc": 8}, {"id": 1236482, "mc": 739, "oc": 167}], "cyanepoli": [{"id": 1014110, "mc": 1801, "oc": 228}], "cyberzone": [{"id": 1018014, "mc": 45, "oc": 15}], "cybergirl": [{"id": 1018014, "mc": 45, "oc": 15}], "cyfrowych": [{"id": 1030690, "mc": 90, "oc": 18}, {"id": 1217822, "mc": 408, "oc": 36}], "cyarin": [{"id": 1033201, "mc": 2293, "oc": 591}], "cypher": [{"id": 1033534, "mc": 7, "oc": 2}, {"id": 1126970, "mc": 24, "oc": 5}, {"id": 1178110, "mc": 28, "oc": 14}], "cybermice": [{"id": 1035135, "mc": 294, "oc": 5}], "cya": [{"id": 1044280, "mc": 95, "oc": 20}, {"id": 1099849, "mc": 76, "oc": 7}, {"id": 1207772, "mc": 196, "oc": 38}], "cyborg": [{"id": 1044515, "mc": 6, "oc": 1}], "cynotao": [{"id": 1053446, "mc": 12, "oc": 3}], "cyno": [{"id": 1053446, "mc": 12, "oc": 3}], "cyprejyo": [{"id": 1054547, "mc": 25, "oc": 15}], "cyru": [{"id": 1055979, "mc": 1794, "oc": 63}, {"id": 1123634, "mc": 1461, "oc": 146}, {"id": 1123634, "mc": 1461, "oc": 146}], "cyborc": [{"id": 1059102, "mc": 1522, "oc": 1}], "cyop": [{"id": 1063274, "mc": 254, "oc": 91}], "cyanlab": [{"id": 1064508, "mc": 2659, "oc": 267}, {"id": 1064508, "mc": 2659, "oc": 267}], "cyano": [{"id": 1069575, "mc": 571, "oc": 75}], "cycling": [{"id": 1079956, "mc": 75, "oc": 3}, {"id": 1079956, "mc": 75, "oc": 3}, {"id": 1108940, "mc": 447, "oc": 15}, {"id": 1138658, "mc": 631, "oc": 35}, {"id": 1239109, "mc": 35, "oc": 2}, {"id": 1240008, "mc": 477, "oc": 30}], "cyberwave": [{"id": 1082817, "mc": 1027, "oc": 141}], "cyberhog": [{"id": 1083661, "mc": 421, "oc": 74}], "cyclop": [{"id": 1087236, "mc": 3373, "oc": 1022}], "cyberheart": [{"id": 1094369, "mc": 479, "oc": 80}], "cyberspace": [{"id": 1097210, "mc": 1238, "oc": 184}, {"id": 1105289, "mc": 72, "oc": 18}, {"id": 1206421, "mc": 23, "oc": 4}], "cynic1254": [{"id": 1099498, "mc": 80, "oc": 28}], "cycle": [{"id": 1106807, "mc": 60, "oc": 5}, {"id": 1119645, "mc": 16796, "oc": 5360}, {"id": 1119645, "mc": 16796, "oc": 5360}, {"id": 1134477, "mc": 85, "oc": 17}, {"id": 1163321, "mc": 84, "oc": 11}, {"id": 1199815, "mc": 26, "oc": 3}, {"id": 1230458, "mc": 4, "oc": 0}, {"id": 1243178, "mc": 332, "oc": 20}], "cybersec": [{"id": 1108859, "mc": 104, "oc": 12}, {"id": 1220971, "mc": 128, "oc": 21}, {"id": 1235628, "mc": 1447, "oc": 91}], "cynicznej": [{"id": 1109202, "mc": 134, "oc": 33}], "cyg2025": [{"id": 1135996, "mc": 109, "oc": 18}], "cybercraft": [{"id": 1138104, "mc": 2601, "oc": 157}], "cybernetic": [{"id": 1139995, "mc": 55, "oc": 17}], "cyberbullying": [{"id": 1141145, "mc": 69, "oc": 24}], "cyclebot": [{"id": 1142101, "mc": 3192, "oc": 16}], "cyberv": [{"id": 1145277, "mc": 1413, "oc": 100}], "cyn": [{"id": 1148813, "mc": 335, "oc": 25}, {"id": 1191355, "mc": 1296, "oc": 135}], "cyclon": [{"id": 1149560, "mc": 1544, "oc": 321}], "cyclone": [{"id": 1149560, "mc": 1544, "oc": 321}], "cybermaike": [{"id": 1155326, "mc": 3219, "oc": 117}], "cykosu": [{"id": 1169028, "mc": 65, "oc": 22}], "cyberpunkish": [{"id": 1172267, "mc": 64, "oc": 24}], "cyberhade": [{"id": 1176912, "mc": 75, "oc": 14}], "cyrax": [{"id": 1179169, "mc": 250, "oc": 19}], "cybernaut": [{"id": 1179753, "mc": 1415, "oc": 290}], "cypopp": [{"id": 1185879, "mc": 604, "oc": 70}], "cy5yxxf5pc": [{"id": 1185978, "mc": 81, "oc": 27}], "cyberware": [{"id": 1189534, "mc": 1019, "oc": 50}], "cynthetic": [{"id": 1191355, "mc": 1296, "oc": 135}], "cyberjunglenft": [{"id": 1195622, "mc": 592, "oc": 3}], "cymru": [{"id": 1201320, "mc": 75, "oc": 13}, {"id": 1201320, "mc": 75, "oc": 13}, {"id": 1201320, "mc": 75, "oc": 13}], "cyanza": [{"id": 1202802, "mc": 29, "oc": 9}], "cynosure": [{"id": 1206456, "mc": 25, "oc": 14}], "cyool": [{"id": 1207777, "mc": 256, "oc": 32}], "cyf": [{"id": 1207896, "mc": 15277, "oc": 583}], "cynz5": [{"id": 1215098, "mc": 12, "oc": 4}], "cynful": [{"id": 1218204, "mc": 12, "oc": 2}], "cynriaaa": [{"id": 1218204, "mc": 12, "oc": 2}], "cybertron": [{"id": 1226562, "mc": 186, "oc": 24}], "cyrob": [{"id": 1230672, "mc": 948, "oc": 107}], "cytooxien": [{"id": 1232498, "mc": 194, "oc": 58}], "cyrtonic": [{"id": 1235016, "mc": 17, "oc": 4}], "cybersportul": [{"id": 1237891, "mc": 913, "oc": 178}], "cybro": [{"id": 1240938, "mc": 43, "oc": 9}], "cydyna": [{"id": 1243868, "mc": 153, "oc": 35}]}