{"gsgzbqhtsf": [{"id": 1000565, "mc": 108, "oc": 20}], "gsw2jasfy3": [{"id": 1000590, "mc": 48, "oc": 3}], "gszxeydrqr": [{"id": 1000599, "mc": 677, "oc": 43}], "gsqmazh": [{"id": 1000925, "mc": 17, "oc": 6}], "gsnpncfu4q": [{"id": 1001090, "mc": 14, "oc": 6}], "gssktbvveh": [{"id": 1001292, "mc": 9, "oc": 2}], "gsexfbftgc": [{"id": 1001811, "mc": 48, "oc": 11}], "gskh9eexmv": [{"id": 1001865, "mc": 106, "oc": 6}], "gszetrk": [{"id": 1002062, "mc": 21, "oc": 0}], "gszvwfnqvk": [{"id": 1002189, "mc": 7, "oc": 4}], "gs6em46": [{"id": 1002246, "mc": 36, "oc": 2}], "gshnhemcn7": [{"id": 1002528, "mc": 121, "oc": 5}], "gsv9ebt26h": [{"id": 1003202, "mc": 165, "oc": 5}], "gsgwtqnsdq": [{"id": 1003553, "mc": 68, "oc": 21}], "gsqphcux6w": [{"id": 1003608, "mc": 41, "oc": 10}], "gskn7dsbry": [{"id": 1003807, "mc": 1, "oc": 1}], "gshmjcg": [{"id": 1004293, "mc": 157, "oc": 21}], "gsjqqafu24": [{"id": 1004548, "mc": 134, "oc": 25}], "gscpwxh": [{"id": 1004744, "mc": 31, "oc": 7}], "gsmu4ptrmf": [{"id": 1005093, "mc": 8, "oc": 6}], "gsmpvwkjvh": [{"id": 1005139, "mc": 100, "oc": 8}], "gsbgj2y": [{"id": 1005189, "mc": 58, "oc": 5}], "gsywsnm": [{"id": 1005362, "mc": 23, "oc": 11}], "gs4dfhvzxd": [{"id": 1005597, "mc": 9, "oc": 1}], "gscgqsxj38": [{"id": 1005672, "mc": 16, "oc": 11}], "gsyxbxvhsz": [{"id": 1005692, "mc": 7, "oc": 4}], "gsggrdvmw": [{"id": 1005741, "mc": 174, "oc": 57}], "gscuefd8fh": [{"id": 1005785, "mc": 7, "oc": 0}], "gsxdfmmsn7": [{"id": 1006634, "mc": 2976, "oc": 533}], "gse5jpwwk": [{"id": 1006704, "mc": 6, "oc": 1}], "gstzegkd3u": [{"id": 1006764, "mc": 654, "oc": 21}], "gstafhrznw": [{"id": 1006888, "mc": 35, "oc": 3}], "gsscptg": [{"id": 1007155, "mc": 25, "oc": 7}], "gscphkdc3q": [{"id": 1007683, "mc": 237, "oc": 10}], "gs3wpcp": [{"id": 1008337, "mc": 58, "oc": 8}], "gsbnd8kmer": [{"id": 1008508, "mc": 21, "oc": 14}], "gski": [{"id": 1008941, "mc": 727, "oc": 43}], "gsrak5f": [{"id": 1009136, "mc": 24, "oc": 4}], "gsv2zdqzz7": [{"id": 1009599, "mc": 15, "oc": 4}], "gstz5re25j": [{"id": 1009761, "mc": 25, "oc": 12}], "gshmk44ts5": [{"id": 1009956, "mc": 42, "oc": 2}], "gsdzpdekpf": [{"id": 1010670, "mc": 14, "oc": 3}], "gsxdx8mwv6": [{"id": 1010913, "mc": 26, "oc": 7}], "gshgrx2ufr": [{"id": 1011060, "mc": 153, "oc": 13}], "gs8z2jd": [{"id": 1011084, "mc": 24, "oc": 4}], "gsqveu5kdk": [{"id": 1011292, "mc": 45, "oc": 5}], "gsxkhmuuzh": [{"id": 1011312, "mc": 2, "oc": 1}], "gsc6dmudrt": [{"id": 1011452, "mc": 1887, "oc": 47}], "gskdspgjqb": [{"id": 1013350, "mc": 56, "oc": 24}], "gsqwukt": [{"id": 1013511, "mc": 7, "oc": 1}], "gsunph6": [{"id": 1013710, "mc": 376, "oc": 65}], "gsxhgp9": [{"id": 1015387, "mc": 206, "oc": 14}], "gspwmtz": [{"id": 1015696, "mc": 3, "oc": 1}], "gsremcdcjc": [{"id": 1015699, "mc": 23, "oc": 0}], "gsvzwgvrth": [{"id": 1016041, "mc": 34, "oc": 13}], "gsqafvhwad": [{"id": 1016239, "mc": 11, "oc": 3}], "gsptpyxzst": [{"id": 1016525, "mc": 116, "oc": 13}], "gsfu2xgubw": [{"id": 1017782, "mc": 769, "oc": 99}], "gsfvgxe": [{"id": 1017863, "mc": 24, "oc": 4}], "gsw26djabu": [{"id": 1018439, "mc": 9, "oc": 2}], "gscupvuxbd": [{"id": 1018854, "mc": 85, "oc": 53}], "gspwc8wu4e": [{"id": 1020723, "mc": 214, "oc": 29}], "gsnvxhfzr": [{"id": 1020984, "mc": 38, "oc": 20}], "gs9f2h99pf": [{"id": 1021199, "mc": 96, "oc": 23}], "gstagzdapc": [{"id": 1022070, "mc": 3987, "oc": 685}], "gsfby89": [{"id": 1022540, "mc": 468, "oc": 98}], "gsqqfnx": [{"id": 1022673, "mc": 150, "oc": 18}], "gsp43pn": [{"id": 1022779, "mc": 187, "oc": 14}], "gsrbheu": [{"id": 1022980, "mc": 174, "oc": 52}], "gs6hsf4pf": [{"id": 1023052, "mc": 300, "oc": 113}], "gstwpwy": [{"id": 1023526, "mc": 33, "oc": 15}], "gskeadqeqb": [{"id": 1023531, "mc": 4, "oc": 0}], "gswzf28": [{"id": 1025312, "mc": 59, "oc": 13}], "gsdh3xe": [{"id": 1025318, "mc": 119, "oc": 3}], "gss6nej": [{"id": 1026403, "mc": 32, "oc": 17}], "gsrejhf4bg": [{"id": 1027641, "mc": 4, "oc": 3}], "gszccs8myn": [{"id": 1028020, "mc": 17, "oc": 5}], "gsatnba": [{"id": 1028600, "mc": 9, "oc": 6}], "gsqh8nc": [{"id": 1028710, "mc": 227, "oc": 21}], "gsuwz2c": [{"id": 1029100, "mc": 28, "oc": 1}], "gs33br5": [{"id": 1029183, "mc": 39, "oc": 12}], "gsaspq398w": [{"id": 1029253, "mc": 9, "oc": 3}], "gseuksrpb7": [{"id": 1029676, "mc": 10, "oc": 2}], "gsmee6yszc": [{"id": 1029879, "mc": 16, "oc": 9}], "gssqfhensb": [{"id": 1029934, "mc": 12, "oc": 3}], "gsntun6rwp": [{"id": 1030149, "mc": 6, "oc": 0}], "gs2waeat6q": [{"id": 1030552, "mc": 68, "oc": 29}], "gsrvrx": [{"id": 1030721, "mc": 1628, "oc": 515}], "gsyvqq6s6w": [{"id": 1030900, "mc": 14, "oc": 7}], "gsc4wpa": [{"id": 1031300, "mc": 211, "oc": 69}], "gsyztpuvqu": [{"id": 1031810, "mc": 1171, "oc": 1}], "gs8drq9bkx": [{"id": 1032615, "mc": 6, "oc": 2}], "gsvqackgvf": [{"id": 1032851, "mc": 9, "oc": 5}], "gspxhfz": [{"id": 1032930, "mc": 1, "oc": 0}], "gspecafujx": [{"id": 1033161, "mc": 904, "oc": 90}], "gsm3gqp": [{"id": 1033274, "mc": 49, "oc": 9}], "gscnsemerh": [{"id": 1034713, "mc": 30, "oc": 11}], "gsjj6csynn": [{"id": 1035288, "mc": 317, "oc": 26}], "gs5csuqy7r": [{"id": 1036374, "mc": 20, "oc": 5}], "gs2kh4v": [{"id": 1036454, "mc": 8, "oc": 2}], "gs3bhc5fdz": [{"id": 1037238, "mc": 42, "oc": 19}], "gszgjuk": [{"id": 1038652, "mc": 46, "oc": 11}], "gsvgxj7jkn": [{"id": 1038687, "mc": 1086, "oc": 66}], "gs4xht5dte": [{"id": 1041407, "mc": 7, "oc": 0}], "gsaj2dc": [{"id": 1042196, "mc": 42, "oc": 10}], "gsh96xz": [{"id": 1042608, "mc": 32, "oc": 9}], "gspxqjn": [{"id": 1042621, "mc": 203, "oc": 44}], "gs9vm8j": [{"id": 1042640, "mc": 10, "oc": 0}], "gsmkv8jwej": [{"id": 1043336, "mc": 1, "oc": 0}], "gsakvfscf8": [{"id": 1043352, "mc": 79, "oc": 6}], "gs4knf6cgz": [{"id": 1044631, "mc": 14, "oc": 4}], "gsvuqjjvx2": [{"id": 1044741, "mc": 39, "oc": 3}], "gsuwfk8ewf": [{"id": 1044963, "mc": 133, "oc": 31}], "gswkvcf": [{"id": 1044970, "mc": 6, "oc": 1}], "gsgmptpkkc": [{"id": 1045858, "mc": 26, "oc": 7}], "gsnke8wrsx": [{"id": 1045912, "mc": 3683, "oc": 19}], "gsmehaweeg": [{"id": 1045944, "mc": 21, "oc": 7}], "gsambfh6vy": [{"id": 1046473, "mc": 21, "oc": 10}], "gsuqwutgav": [{"id": 1046487, "mc": 47, "oc": 3}], "gstf6tnbr7": [{"id": 1046748, "mc": 10, "oc": 4}], "gs4hge8p8q": [{"id": 1049252, "mc": 74, "oc": 13}], "gsuqfrhfbv": [{"id": 1049511, "mc": 1003, "oc": 9}], "gsqftd8czz": [{"id": 1050752, "mc": 5, "oc": 1}], "gssbmvt": [{"id": 1051461, "mc": 11, "oc": 8}], "gsfxc6cfvf": [{"id": 1051944, "mc": 106, "oc": 10}], "gstgtsuaqf": [{"id": 1052018, "mc": 63, "oc": 14}], "gszjyvcvtp": [{"id": 1052718, "mc": 7, "oc": 0}], "gsdevne7bn": [{"id": 1052919, "mc": 26, "oc": 8}], "gstczfd6hx": [{"id": 1053434, "mc": 73, "oc": 6}], "gsbqw2m": [{"id": 1053692, "mc": 62, "oc": 20}], "gswztdv": [{"id": 1054518, "mc": 31, "oc": 8}], "gsrrhth": [{"id": 1055219, "mc": 1, "oc": 0}], "gsyjxdu9yv": [{"id": 1055647, "mc": 3, "oc": 0}], "gspj5hjwgt": [{"id": 1055746, "mc": 5, "oc": 3}], "gs4jrte": [{"id": 1056095, "mc": 1186, "oc": 186}], "gsqy3p7ynb": [{"id": 1056987, "mc": 6, "oc": 0}], "gsnk98zqn2": [{"id": 1057256, "mc": 2, "oc": 2}], "gsvrsnwzkw": [{"id": 1057723, "mc": 34, "oc": 5}], "gsdtknf": [{"id": 1058100, "mc": 6, "oc": 1}], "gspaaac": [{"id": 1059598, "mc": 3, "oc": 2}], "gsymgafjxf": [{"id": 1059675, "mc": 52, "oc": 19}], "gsz77jmkjk": [{"id": 1059836, "mc": 27, "oc": 2}], "gspm5crjmk": [{"id": 1060413, "mc": 4, "oc": 2}], "gs9sqxe": [{"id": 1060586, "mc": 16, "oc": 2}], "gsgsufc8dj": [{"id": 1060649, "mc": 1945, "oc": 132}], "gspnu5s6wp": [{"id": 1060844, "mc": 79, "oc": 18}], "gsfuahzceb": [{"id": 1062077, "mc": 1248, "oc": 34}], "gsmp5qjxtq": [{"id": 1062410, "mc": 114, "oc": 9}], "gsygqzmv9p": [{"id": 1063096, "mc": 122, "oc": 26}], "gszqqgjeqk": [{"id": 1063472, "mc": 686, "oc": 67}], "gsnjztd": [{"id": 1063519, "mc": 46, "oc": 12}], "gsqnjmzjbz": [{"id": 1064538, "mc": 334, "oc": 53}], "gscpfmt": [{"id": 1064603, "mc": 259, "oc": 16}], "gszzfuxnsw": [{"id": 1065961, "mc": 7, "oc": 5}], "gsur4t9": [{"id": 1066181, "mc": 4, "oc": 0}], "gssfrdveqy": [{"id": 1066632, "mc": 4, "oc": 2}], "gshhmw": [{"id": 1067108, "mc": 1246, "oc": 40}], "gsngbhf": [{"id": 1067552, "mc": 4, "oc": 0}], "gse3bguh7m": [{"id": 1068078, "mc": 921, "oc": 194}], "gskc99pznq": [{"id": 1068188, "mc": 27, "oc": 15}], "gsyg4w4": [{"id": 1068443, "mc": 51, "oc": 6}], "gstcjagxd5": [{"id": 1068506, "mc": 83, "oc": 9}], "gsh3zkwxyj": [{"id": 1068757, "mc": 421, "oc": 35}], "gs5a7v7zr5": [{"id": 1068774, "mc": 92, "oc": 21}], "gse62weptp": [{"id": 1070561, "mc": 75, "oc": 5}], "gszkqyc": [{"id": 1070674, "mc": 33, "oc": 8}], "gs83sqp": [{"id": 1071046, "mc": 40, "oc": 6}], "gsn": [{"id": 1071087, "mc": 2627, "oc": 585}], "gsfynx8rqb": [{"id": 1071627, "mc": 39, "oc": 12}], "gsypfwatzq": [{"id": 1072319, "mc": 28, "oc": 4}], "gs8gxmg": [{"id": 1072458, "mc": 1, "oc": 0}], "gs86ch84nn": [{"id": 1072976, "mc": 32, "oc": 6}], "gsjktn3": [{"id": 1074530, "mc": 2, "oc": 0}], "gshmhws5xb": [{"id": 1075176, "mc": 80, "oc": 27}], "gsk82ky": [{"id": 1075219, "mc": 422, "oc": 21}], "gsqfgvn": [{"id": 1075291, "mc": 1, "oc": 0}], "gsn8e4csj5": [{"id": 1075470, "mc": 2, "oc": 0}], "gsx28fh": [{"id": 1075688, "mc": 37, "oc": 10}], "gswsjgqh3k": [{"id": 1075752, "mc": 18, "oc": 6}], "gsusbgdeju": [{"id": 1076337, "mc": 15, "oc": 9}], "gskm6dw62k": [{"id": 1077209, "mc": 13, "oc": 3}], "gszdcpepnt": [{"id": 1077903, "mc": 81, "oc": 9}], "gs3vhqgsfy": [{"id": 1078273, "mc": 164, "oc": 14}], "gsjmke4v7m": [{"id": 1078597, "mc": 148, "oc": 47}], "gsa5cuk": [{"id": 1078918, "mc": 23, "oc": 6}], "gsvgawu": [{"id": 1079290, "mc": 2, "oc": 0}], "gszeamwumg": [{"id": 1079548, "mc": 14, "oc": 7}], "gsrhpch": [{"id": 1079834, "mc": 1, "oc": 0}], "gsrfydrwcz": [{"id": 1079963, "mc": 14, "oc": 7}], "gsaeysn": [{"id": 1080582, "mc": 14, "oc": 3}], "gsaatfj": [{"id": 1081127, "mc": 182, "oc": 5}], "gs7ewmps5f": [{"id": 1081515, "mc": 24, "oc": 2}], "gskdfwb4wa": [{"id": 1082278, "mc": 227, "oc": 48}], "gsscwufaba": [{"id": 1083056, "mc": 162, "oc": 58}], "gspwp2753v": [{"id": 1083240, "mc": 1981, "oc": 13}], "gsy3e5ngmu": [{"id": 1083465, "mc": 44, "oc": 5}], "gsfyekw5gm": [{"id": 1084651, "mc": 16, "oc": 8}], "gsxgxrvgtj": [{"id": 1085104, "mc": 638, "oc": 13}], "gsmgwjjnwa": [{"id": 1087294, "mc": 6, "oc": 2}], "gsvq3zjxj7": [{"id": 1088412, "mc": 188, "oc": 46}], "gsjz2su9ay": [{"id": 1088563, "mc": 177, "oc": 63}], "gskdauczwt": [{"id": 1088635, "mc": 1551, "oc": 116}], "gsdrqdukhp": [{"id": 1088681, "mc": 30, "oc": 4}], "gsfnze5xyj": [{"id": 1089457, "mc": 42, "oc": 16}], "gsrpqmnnpw": [{"id": 1090708, "mc": 55, "oc": 5}], "gs6wwmdxcn": [{"id": 1091405, "mc": 1, "oc": 0}], "gsmrc5azcv": [{"id": 1092127, "mc": 44, "oc": 12}], "gs43dqqhfa": [{"id": 1092287, "mc": 25, "oc": 2}], "gstrcpd": [{"id": 1092569, "mc": 10, "oc": 1}], "gs9rsg7pr8": [{"id": 1093445, "mc": 297, "oc": 17}], "gswepcv": [{"id": 1093673, "mc": 2, "oc": 0}], "gs49xgykmv": [{"id": 1094287, "mc": 7, "oc": 1}], "gsva45nutk": [{"id": 1094322, "mc": 14, "oc": 0}], "gsgvfun": [{"id": 1094367, "mc": 4, "oc": 0}], "gsynm5j6tm": [{"id": 1094884, "mc": 100, "oc": 12}], "gsjvdcn": [{"id": 1095246, "mc": 4, "oc": 0}], "gsmpbz9": [{"id": 1095405, "mc": 1, "oc": 0}], "gsk2a98nt6": [{"id": 1095440, "mc": 7, "oc": 2}], "gsdqxwmtx": [{"id": 1095770, "mc": 127, "oc": 23}], "gs9xqmqxnn": [{"id": 1096938, "mc": 5, "oc": 0}], "gsyew9p": [{"id": 1097416, "mc": 281, "oc": 74}], "gskj5r9": [{"id": 1098031, "mc": 15, "oc": 2}], "gsrjmxjnzj": [{"id": 1098060, "mc": 203, "oc": 15}], "gsun5a": [{"id": 1098516, "mc": 39, "oc": 6}], "gsjfdtj": [{"id": 1099200, "mc": 21, "oc": 4}], "gsept8rqtq": [{"id": 1099363, "mc": 81, "oc": 11}], "gs2csc5h5h": [{"id": 1099663, "mc": 86, "oc": 31}], "gsrh2mjr4c": [{"id": 1100068, "mc": 20, "oc": 5}], "gs5xduj": [{"id": 1100334, "mc": 50, "oc": 9}], "gshtfjwewe": [{"id": 1100568, "mc": 288, "oc": 46}], "gsnfjk2jqb": [{"id": 1100669, "mc": 225, "oc": 4}], "gsbdfdx": [{"id": 1100681, "mc": 2, "oc": 0}], "gs7s6sxch7": [{"id": 1100988, "mc": 4, "oc": 2}], "gsq98ux2dm": [{"id": 1101323, "mc": 707, "oc": 69}], "gsyabxh": [{"id": 1101826, "mc": 112, "oc": 7}], "gswdrm2": [{"id": 1103591, "mc": 45, "oc": 12}], "gsq2cmjjxe": [{"id": 1103610, "mc": 413, "oc": 26}], "gs4fbwdgag": [{"id": 1103694, "mc": 60, "oc": 16}], "gs7gbs2quk": [{"id": 1104060, "mc": 129, "oc": 9}], "gs73jncv3f": [{"id": 1104624, "mc": 152, "oc": 14}], "gspjwa7fcq": [{"id": 1105215, "mc": 298, "oc": 26}], "gsds8trhrx": [{"id": 1105800, "mc": 39, "oc": 9}], "gs8hqsre8w": [{"id": 1106096, "mc": 106, "oc": 15}], "gscnuma": [{"id": 1106622, "mc": 1, "oc": 0}], "gsusdbdptq": [{"id": 1107289, "mc": 77, "oc": 11}], "gsftpsj": [{"id": 1108851, "mc": 11, "oc": 3}], "gsgfmpn2jf": [{"id": 1109255, "mc": 12, "oc": 6}], "gs7tjxu5kp": [{"id": 1109850, "mc": 13, "oc": 1}], "gswqyruvjt": [{"id": 1109860, "mc": 5, "oc": 1}], "gsnkux9xyw": [{"id": 1110384, "mc": 144, "oc": 24}], "gsyyjeyze8": [{"id": 1111910, "mc": 2, "oc": 0}], "gszg5t6wfa": [{"id": 1111946, "mc": 901, "oc": 27}], "gsdtntx6bx": [{"id": 1112657, "mc": 94, "oc": 15}], "gsvg6fn45p": [{"id": 1113777, "mc": 266, "oc": 32}], "gs8sfqwm6z": [{"id": 1115093, "mc": 88, "oc": 32}], "gs9fsxb": [{"id": 1115306, "mc": 32, "oc": 3}], "gs7ggzyemc": [{"id": 1153483, "mc": 136, "oc": 22}], "gs9rhmyry9": [{"id": 1153484, "mc": 52, "oc": 26}], "gs8chbtgkv": [{"id": 1153485, "mc": 184, "oc": 89}], "gshmdjfgpb": [{"id": 1153494, "mc": 20, "oc": 3}], "gspm6gxw5b": [{"id": 1153497, "mc": 49, "oc": 7}], "gsycabhcxm": [{"id": 1153502, "mc": 54, "oc": 5}], "gsk8nzbxgh": [{"id": 1153511, "mc": 25, "oc": 5}], "gsxkbs2gzc": [{"id": 1153517, "mc": 12, "oc": 6}], "gs2xxqhspa": [{"id": 1153522, "mc": 906, "oc": 149}], "gs3eeukd": [{"id": 1153532, "mc": 10, "oc": 1}], "gs8xg8rmjr": [{"id": 1153533, "mc": 36, "oc": 7}], "gsfq3zz": [{"id": 1153535, "mc": 313, "oc": 36}], "gsr4qnaq9v": [{"id": 1153544, "mc": 65, "oc": 8}], "gsrvxqkhkq": [{"id": 1153550, "mc": 80, "oc": 14}], "gsjtpkmjhz": [{"id": 1153557, "mc": 1, "oc": 1}], "gsp2wnccwq": [{"id": 1153565, "mc": 10, "oc": 0}], "gs2fkwgyfn": [{"id": 1153574, "mc": 80, "oc": 5}], "gskdmvvnyg": [{"id": 1153578, "mc": 120, "oc": 39}], "gsqkdnbxvc": [{"id": 1153586, "mc": 15, "oc": 6}], "gsteyu8tua": [{"id": 1153587, "mc": 29, "oc": 9}], "gsy8h5ympb": [{"id": 1153595, "mc": 13, "oc": 0}], "gsc7mjgnn6": [{"id": 1153596, "mc": 39, "oc": 2}], "gsbbqn6q3r": [{"id": 1153598, "mc": 21, "oc": 9}], "gsjmwzb6b9": [{"id": 1153609, "mc": 25, "oc": 7}], "gsxm5tu4ef": [{"id": 1153617, "mc": 114, "oc": 23}], "gs5a85ymkn": [{"id": 1153618, "mc": 71, "oc": 31}], "gsvbzja": [{"id": 1153646, "mc": 66, "oc": 12}], "gseb4mpxme": [{"id": 1153651, "mc": 18, "oc": 3}], "gsb9ndw3bv": [{"id": 1153657, "mc": 1, "oc": 0}], "gsfjehxyrr": [{"id": 1153676, "mc": 53, "oc": 11}], "gsuqpukhaw": [{"id": 1153685, "mc": 8, "oc": 2}], "gsaw4rr5nb": [{"id": 1153696, "mc": 124, "oc": 21}], "gssbedcdvw": [{"id": 1153705, "mc": 105, "oc": 4}], "gszrq5jx2c": [{"id": 1153710, "mc": 45, "oc": 17}], "gsbpn8sjsm": [{"id": 1153726, "mc": 57, "oc": 11}], "gs9bsz3egr": [{"id": 1153749, "mc": 213, "oc": 47}], "gsbpzvmmwz": [{"id": 1153756, "mc": 11, "oc": 3}], "gsknuxubzk": [{"id": 1153759, "mc": 124, "oc": 17}], "gsksjcgu4r": [{"id": 1153760, "mc": 18, "oc": 5}], "gs3tkttekw": [{"id": 1153775, "mc": 32, "oc": 4}], "gsrjfsxcjr": [{"id": 1153796, "mc": 17, "oc": 3}], "gstneddw2r": [{"id": 1153821, "mc": 41, "oc": 12}], "gswxzzxdqh": [{"id": 1153829, "mc": 973, "oc": 210}], "gstg6xdasv": [{"id": 1153837, "mc": 13, "oc": 5}], "gs8dznujm6": [{"id": 1153850, "mc": 10, "oc": 4}], "gsrx368qgk": [{"id": 1153891, "mc": 206, "oc": 33}], "gsxbseavm6": [{"id": 1153892, "mc": 22, "oc": 4}], "gsm7jmn8cq": [{"id": 1153893, "mc": 68, "oc": 16}], "gs94mhehgz": [{"id": 1153896, "mc": 3, "oc": 0}], "gsguhzhfm3": [{"id": 1153902, "mc": 57, "oc": 10}], "gszfy5sgz3": [{"id": 1153944, "mc": 31, "oc": 6}], "gsfmnznung": [{"id": 1153948, "mc": 164, "oc": 43}], "gsa39sv9t7": [{"id": 1153989, "mc": 23, "oc": 3}], "gssxaupe7u": [{"id": 1154019, "mc": 23, "oc": 5}], "gsxbm8jxen": [{"id": 1154070, "mc": 1141, "oc": 118}], "gsegtddcpq": [{"id": 1154103, "mc": 36, "oc": 6}], "gsvdzyd": [{"id": 1154154, "mc": 4, "oc": 0}], "gs8rqke6d": [{"id": 1154219, "mc": 2, "oc": 0}], "gsywxcc6bq": [{"id": 1154224, "mc": 8, "oc": 1}], "gs2jpqaxvd": [{"id": 1154558, "mc": 17, "oc": 2}], "gsk85dhkse": [{"id": 1154567, "mc": 37, "oc": 11}], "gsvnwecmfd": [{"id": 1154569, "mc": 319, "oc": 46}], "gsbyef2bx8": [{"id": 1154577, "mc": 1, "oc": 0}], "gs4gtmsjjt": [{"id": 1154583, "mc": 52, "oc": 24}], "gsx4qat": [{"id": 1154587, "mc": 566, "oc": 96}], "gs8egffrnb": [{"id": 1154589, "mc": 26, "oc": 7}], "gsf5rbw7ky": [{"id": 1154595, "mc": 50, "oc": 6}], "gsfeprqaeu": [{"id": 1154603, "mc": 191, "oc": 13}], "gskz5aymf7": [{"id": 1154606, "mc": 188, "oc": 51}], "gsycybkmda": [{"id": 1154607, "mc": 28, "oc": 10}], "gsa2gb8qyg": [{"id": 1154612, "mc": 2, "oc": 0}], "gszn4zzamf": [{"id": 1154614, "mc": 81, "oc": 12}], "gstdqygaww": [{"id": 1154624, "mc": 186, "oc": 29}], "gspcqhfseb": [{"id": 1154627, "mc": 5, "oc": 0}], "gssvszgkdr": [{"id": 1154632, "mc": 183, "oc": 17}], "gs3btm4rs8": [{"id": 1154634, "mc": 53, "oc": 17}], "gs6aqephjk": [{"id": 1154639, "mc": 166, "oc": 37}], "gswanxecqc": [{"id": 1154652, "mc": 69, "oc": 10}], "gskhhtun3u": [{"id": 1154684, "mc": 104, "oc": 26}], "gshytdagk6": [{"id": 1154685, "mc": 11, "oc": 0}], "gsxqt9wya9": [{"id": 1154703, "mc": 29, "oc": 12}], "gsv3hb9qp": [{"id": 1154725, "mc": 63, "oc": 6}], "gsebjhtysm": [{"id": 1154726, "mc": 33, "oc": 5}], "gs25zarstn": [{"id": 1154752, "mc": 108, "oc": 22}], "gs5qjkfqkm": [{"id": 1154758, "mc": 94, "oc": 32}], "gsxepgdtmg": [{"id": 1154769, "mc": 178, "oc": 30}], "gsf7tq4sw": [{"id": 1154785, "mc": 69, "oc": 9}], "gsy9ejhqv6": [{"id": 1154809, "mc": 43, "oc": 15}], "gs6wywbsjd": [{"id": 1154812, "mc": 24, "oc": 14}], "gszwcuabh5": [{"id": 1154813, "mc": 928, "oc": 103}], "gs5hsvr3c3": [{"id": 1154818, "mc": 94, "oc": 24}], "gs48cmgb4y": [{"id": 1154824, "mc": 50, "oc": 22}], "gsyex9fqtb": [{"id": 1154829, "mc": 258, "oc": 32}], "gshvxf7s3w": [{"id": 1154852, "mc": 29, "oc": 1}], "gskyhgz73e": [{"id": 1154853, "mc": 20, "oc": 6}], "gswwzcw2vn": [{"id": 1154904, "mc": 33, "oc": 8}], "gscqzhenr6": [{"id": 1154926, "mc": 16, "oc": 1}], "gspd9skkzz": [{"id": 1154935, "mc": 61, "oc": 17}], "gssm6hybsk": [{"id": 1154937, "mc": 84, "oc": 18}], "gsmrbdthhd": [{"id": 1155061, "mc": 309, "oc": 54}], "gsyxzvzwme": [{"id": 1155101, "mc": 37, "oc": 11}], "gsvjvmhrbd": [{"id": 1155139, "mc": 108, "oc": 20}], "gshm8ruumm": [{"id": 1155185, "mc": 32, "oc": 17}], "gstekmdjvm": [{"id": 1155198, "mc": 38, "oc": 4}], "gsrtfkssjy": [{"id": 1155228, "mc": 9, "oc": 5}], "gs9wcqjave": [{"id": 1155461, "mc": 497, "oc": 55}], "gsxjr6c7vp": [{"id": 1155609, "mc": 127, "oc": 29}], "gs3psdbv4a": [{"id": 1216704, "mc": 22, "oc": 7}], "gsv6bj4xvq": [{"id": 1216711, "mc": 41, "oc": 13}], "gszbmur369": [{"id": 1216713, "mc": 28, "oc": 9}], "gsq4p43cdm": [{"id": 1216721, "mc": 372, "oc": 32}], "gs6qa8k8bw": [{"id": 1216728, "mc": 93, "oc": 18}], "gsb6e94fen": [{"id": 1216734, "mc": 75, "oc": 13}], "gs7h3py": [{"id": 1216744, "mc": 53, "oc": 2}], "gsa6yyvkwv": [{"id": 1216747, "mc": 34, "oc": 14}], "gscaudmpz8": [{"id": 1216752, "mc": 200, "oc": 35}], "gsqkhhhd7v": [{"id": 1216758, "mc": 662, "oc": 36}], "gspb8wgwpe": [{"id": 1216759, "mc": 70, "oc": 17}], "gsgdjyazhv": [{"id": 1216760, "mc": 279, "oc": 18}], "gsurangnje": [{"id": 1216767, "mc": 11, "oc": 1}], "gssacgy5px": [{"id": 1216771, "mc": 54, "oc": 15}], "gshtstyty2": [{"id": 1216783, "mc": 156, "oc": 14}], "gseaa4emcp": [{"id": 1216811, "mc": 176, "oc": 60}], "gsfxu7eyt7": [{"id": 1216817, "mc": 133, "oc": 20}], "gsc2rhcm5k": [{"id": 1216821, "mc": 88, "oc": 27}], "gsmk7vcptk": [{"id": 1216842, "mc": 365, "oc": 86}], "gs9mr7hjxu": [{"id": 1216855, "mc": 54, "oc": 15}], "gsh2gkfnpt": [{"id": 1216872, "mc": 10, "oc": 5}], "gsyacn28d3": [{"id": 1216901, "mc": 91, "oc": 6}], "gsbzdyc4f7": [{"id": 1216950, "mc": 129, "oc": 27}], "gsatp98wfz": [{"id": 1216953, "mc": 51, "oc": 15}], "gsgqkvewtq": [{"id": 1216997, "mc": 72, "oc": 14}], "gsuu8wwsgu": [{"id": 1217043, "mc": 69, "oc": 13}], "gsnxdqp37e": [{"id": 1217099, "mc": 366, "oc": 29}], "gsbnbtucet": [{"id": 1217115, "mc": 155, "oc": 14}], "gskb92eg4d": [{"id": 1217126, "mc": 29, "oc": 4}], "gs5u683qh4": [{"id": 1217153, "mc": 10, "oc": 0}], "gs7w9bgmkt": [{"id": 1217225, "mc": 16, "oc": 4}], "gsq9uefcbj": [{"id": 1217253, "mc": 145, "oc": 45}], "gsewrqhckf": [{"id": 1217306, "mc": 42, "oc": 17}], "gssevwauz6": [{"id": 1217316, "mc": 18, "oc": 5}], "gspnznbfcw": [{"id": 1217590, "mc": 858, "oc": 112}], "gsnnghu29g": [{"id": 1217767, "mc": 21, "oc": 9}], "gs": [{"id": 1217878, "mc": 3040, "oc": 114}], "gs4vsqubad": [{"id": 1217886, "mc": 6, "oc": 0}], "gsg3h39ehx": [{"id": 1217890, "mc": 1, "oc": 1}], "gsfnwpsezh": [{"id": 1217892, "mc": 145, "oc": 23}], "gsmnbpd": [{"id": 1217896, "mc": 51, "oc": 1}], "gsp3shq7uz": [{"id": 1217897, "mc": 192, "oc": 44}], "gsu2x7q9dz": [{"id": 1217900, "mc": 126, "oc": 45}], "gswbjwxzt": [{"id": 1217906, "mc": 14, "oc": 1}], "gsxah3beep": [{"id": 1217910, "mc": 146, "oc": 30}], "gscxve2ewu": [{"id": 1217914, "mc": 8, "oc": 5}], "gszmt88kzt": [{"id": 1217916, "mc": 164, "oc": 55}], "gsl": [{"id": 1217917, "mc": 1802, "oc": 228}], "gsjuuqawp5": [{"id": 1217919, "mc": 237, "oc": 38}], "gsqxk9v8a6": [{"id": 1217924, "mc": 1172, "oc": 257}], "gsgkcetzkg": [{"id": 1217927, "mc": 48, "oc": 9}], "gstg": [{"id": 1217932, "mc": 347, "oc": 87}], "gsxm7da": [{"id": 1217935, "mc": 167, "oc": 51}], "gsnvvqcwgx": [{"id": 1217949, "mc": 66, "oc": 4}], "gshbvacpma": [{"id": 1217950, "mc": 73, "oc": 11}], "gsyc857p8b": [{"id": 1217964, "mc": 68, "oc": 22}], "gsgkrnader": [{"id": 1217966, "mc": 135, "oc": 19}], "gsb9kgcbp": [{"id": 1217969, "mc": 36, "oc": 6}], "gsynwbevvk": [{"id": 1217984, "mc": 326, "oc": 40}], "gsyncdev": [{"id": 1217986, "mc": 34, "oc": 1}], "gsdpsxuuwn": [{"id": 1217998, "mc": 39, "oc": 15}], "gsuecem6kv": [{"id": 1218021, "mc": 57, "oc": 8}], "gsknhcbwk6": [{"id": 1218023, "mc": 324, "oc": 61}], "gsrhcv5qeb": [{"id": 1218025, "mc": 65, "oc": 16}], "gsfzckacpc": [{"id": 1218037, "mc": 56, "oc": 21}], "gsktxetvsg": [{"id": 1218041, "mc": 114, "oc": 44}], "gsywyskurj": [{"id": 1218047, "mc": 38, "oc": 8}], "gsuthrkze": [{"id": 1218087, "mc": 91, "oc": 16}], "gsmuq3qmsz": [{"id": 1218094, "mc": 124, "oc": 34}], "gs6cnjdmgv": [{"id": 1218106, "mc": 146, "oc": 26}], "gsgh24m7gm": [{"id": 1218112, "mc": 358, "oc": 58}], "gsptbfsdat": [{"id": 1218119, "mc": 684, "oc": 145}], "gsrc": [{"id": 1218138, "mc": 107, "oc": 15}], "gszmad269b": [{"id": 1218190, "mc": 219, "oc": 17}], "gsbfnvw9ux": [{"id": 1218198, "mc": 7, "oc": 4}], "gszdpvtptx": [{"id": 1218206, "mc": 9, "oc": 2}], "gsdtmkf8rf": [{"id": 1218211, "mc": 219, "oc": 31}], "gspagrhudn": [{"id": 1218298, "mc": 160, "oc": 14}], "gsgvh9nnyu": [{"id": 1218300, "mc": 90, "oc": 3}], "gsv5kjupbb": [{"id": 1218321, "mc": 9, "oc": 0}], "gsur2rewdm": [{"id": 1218382, "mc": 40, "oc": 15}], "gsmfukvr9t": [{"id": 1218385, "mc": 32, "oc": 12}], "gsqpdyr3yq": [{"id": 1218390, "mc": 194, "oc": 14}], "gspqz6yzbb": [{"id": 1218396, "mc": 6, "oc": 0}], "gsrp2018": [{"id": 1218401, "mc": 4479, "oc": 886}], "gsnzz6ztvv": [{"id": 1218492, "mc": 38, "oc": 4}], "gsfatw7r95": [{"id": 1218500, "mc": 12, "oc": 0}], "gsw8zwjbej": [{"id": 1218671, "mc": 28, "oc": 7}], "gsfwmztevy": [{"id": 1218813, "mc": 50, "oc": 7}]}